[
    {
        "muhtarlik_ID": 74343,
        "min_SANDIK_NO": "1069",
        "max_SANDIK_NO": "1070",
        "muhtarlik_ADI": "ADİLHAN KÖYÜ",
        "cezaevi_ID": 0,
        "id": "237_0_1360",
        "birim_ID": 1360,
        "ilce_ID": 237,
        "ilce_ADI": null,
        "belde_ID": 0,
        "secim_CEVRESI_ID": 0,
        "yerlesim_YERI_TURU": 0,
        "secilecek_ADAY_SAYISI": 0,
        "il_ID": 17,
        "il_ADI": null,
        "secim_DETAY_ID": 0
    },
    {
        "muhtarlik_ID": 87183,
        "min_SANDIK_NO": "1001",
        "max_SANDIK_NO": "1009",
        "muhtarlik_ADI": "ALAEDDİN MAH.",
        "cezaevi_ID": 0,
        "id": "237_0_1360",
        "birim_ID": 1360,
        "ilce_ID": 237,
        "ilce_ADI": null,
        "belde_ID": 0,
        "secim_CEVRESI_ID": 0,
        "yerlesim_YERI_TURU": 0,
        "secilecek_ADAY_SAYISI": 0,
        "il_ID": 17,
        "il_ADI": null,
        "secim_DETAY_ID": 0
    },
    {
        "muhtarlik_ID": 87188,
        "min_SANDIK_NO": "1071",
        "max_SANDIK_NO": "1072",
        "muhtarlik_ADI": "BAYIRKÖY",
        "cezaevi_ID": 0,
        "id": "237_0_1360",
        "birim_ID": 1360,
        "ilce_ID": 237,
        "ilce_ADI": null,
        "belde_ID": 0,
        "secim_CEVRESI_ID": 0,
        "yerlesim_YERI_TURU": 0,
        "secilecek_ADAY_SAYISI": 0,
        "il_ID": 17,
        "il_ADI": null,
        "secim_DETAY_ID": 0
    },
    {
        "muhtarlik_ID": 74344,
        "min_SANDIK_NO": "1073",
        "max_SANDIK_NO": "1074",
        "muhtarlik_ADI": "BAYRAMİÇ KÖYÜ",
        "cezaevi_ID": 0,
        "id": "237_0_1360",
        "birim_ID": 1360,
        "ilce_ID": 237,
        "ilce_ADI": null,
        "belde_ID": 0,
        "secim_CEVRESI_ID": 0,
        "yerlesim_YERI_TURU": 0,
        "secilecek_ADAY_SAYISI": 0,
        "il_ID": 17,
        "il_ADI": null,
        "secim_DETAY_ID": 0
    },
    {
        "muhtarlik_ID": 72826,
        "min_SANDIK_NO": "1058",
        "max_SANDIK_NO": "1058",
        "muhtarlik_ADI": "BOLAYIR-CAMİİKEBİR MAH.",
        "cezaevi_ID": 0,
        "id": "237_0_1360",
        "birim_ID": 1360,
        "ilce_ID": 237,
        "ilce_ADI": null,
        "belde_ID": 0,
        "secim_CEVRESI_ID": 0,
        "yerlesim_YERI_TURU": 0,
        "secilecek_ADAY_SAYISI": 0,
        "il_ID": 17,
        "il_ADI": null,
        "secim_DETAY_ID": 0
    },
    {
        "muhtarlik_ID": 72827,
        "min_SANDIK_NO": "1059",
        "max_SANDIK_NO": "1059",
        "muhtarlik_ADI": "BOLAYIR-FEVZİÇAKMAK MAH.",
        "cezaevi_ID": 0,
        "id": "237_0_1360",
        "birim_ID": 1360,
        "ilce_ID": 237,
        "ilce_ADI": null,
        "belde_ID": 0,
        "secim_CEVRESI_ID": 0,
        "yerlesim_YERI_TURU": 0,
        "secilecek_ADAY_SAYISI": 0,
        "il_ID": 17,
        "il_ADI": null,
        "secim_DETAY_ID": 0
    },
    {
        "muhtarlik_ID": 72828,
        "min_SANDIK_NO": "1060",
        "max_SANDIK_NO": "1061",
        "muhtarlik_ADI": "BOLAYIR-GAZİSÜLEYMANPAŞA MAH.",
        "cezaevi_ID": 0,
        "id": "237_0_1360",
        "birim_ID": 1360,
        "ilce_ID": 237,
        "ilce_ADI": null,
        "belde_ID": 0,
        "secim_CEVRESI_ID": 0,
        "yerlesim_YERI_TURU": 0,
        "secilecek_ADAY_SAYISI": 0,
        "il_ID": 17,
        "il_ADI": null,
        "secim_DETAY_ID": 0
    },
    {
        "muhtarlik_ID": 87189,
        "min_SANDIK_NO": "1075",
        "max_SANDIK_NO": "1075",
        "muhtarlik_ADI": "BURHANLI KÖYÜ",
        "cezaevi_ID": 0,
        "id": "237_0_1360",
        "birim_ID": 1360,
        "ilce_ID": 237,
        "ilce_ADI": null,
        "belde_ID": 0,
        "secim_CEVRESI_ID": 0,
        "yerlesim_YERI_TURU": 0,
        "secilecek_ADAY_SAYISI": 0,
        "il_ID": 17,
        "il_ADI": null,
        "secim_DETAY_ID": 0
    },
    {
        "muhtarlik_ID": 87184,
        "min_SANDIK_NO": "1010",
        "max_SANDIK_NO": "1024",
        "muhtarlik_ADI": "CAMİİKEBİR MAH.",
        "cezaevi_ID": 0,
        "id": "237_0_1360",
        "birim_ID": 1360,
        "ilce_ID": 237,
        "ilce_ADI": null,
        "belde_ID": 0,
        "secim_CEVRESI_ID": 0,
        "yerlesim_YERI_TURU": 0,
        "secilecek_ADAY_SAYISI": 0,
        "il_ID": 17,
        "il_ADI": null,
        "secim_DETAY_ID": 0
    },
    {
        "muhtarlik_ID": 87190,
        "min_SANDIK_NO": "1076",
        "max_SANDIK_NO": "1076",
        "muhtarlik_ADI": "CEVİZLİ KÖYÜ",
        "cezaevi_ID": 0,
        "id": "237_0_1360",
        "birim_ID": 1360,
        "ilce_ID": 237,
        "ilce_ADI": null,
        "belde_ID": 0,
        "secim_CEVRESI_ID": 0,
        "yerlesim_YERI_TURU": 0,
        "secilecek_ADAY_SAYISI": 0,
        "il_ID": 17,
        "il_ADI": null,
        "secim_DETAY_ID": 0
    },
    {
        "muhtarlik_ID": 87191,
        "min_SANDIK_NO": "1077",
        "max_SANDIK_NO": "1077",
        "muhtarlik_ADI": "CUMALI KÖYÜ",
        "cezaevi_ID": 0,
        "id": "237_0_1360",
        "birim_ID": 1360,
        "ilce_ID": 237,
        "ilce_ADI": null,
        "belde_ID": 0,
        "secim_CEVRESI_ID": 0,
        "yerlesim_YERI_TURU": 0,
        "secilecek_ADAY_SAYISI": 0,
        "il_ID": 17,
        "il_ADI": null,
        "secim_DETAY_ID": 0
    },
    {
        "muhtarlik_ID": 74345,
        "min_SANDIK_NO": "1078",
        "max_SANDIK_NO": "1078",
        "muhtarlik_ADI": "ÇOKAL KÖYÜ",
        "cezaevi_ID": 0,
        "id": "237_0_1360",
        "birim_ID": 1360,
        "ilce_ID": 237,
        "ilce_ADI": null,
        "belde_ID": 0,
        "secim_CEVRESI_ID": 0,
        "yerlesim_YERI_TURU": 0,
        "secilecek_ADAY_SAYISI": 0,
        "il_ID": 17,
        "il_ADI": null,
        "secim_DETAY_ID": 0
    },
    {
        "muhtarlik_ID": 87192,
        "min_SANDIK_NO": "1079",
        "max_SANDIK_NO": "1080",
        "muhtarlik_ADI": "DEĞİRMENDÜZÜ KÖYÜ",
        "cezaevi_ID": 0,
        "id": "237_0_1360",
        "birim_ID": 1360,
        "ilce_ID": 237,
        "ilce_ADI": null,
        "belde_ID": 0,
        "secim_CEVRESI_ID": 0,
        "yerlesim_YERI_TURU": 0,
        "secilecek_ADAY_SAYISI": 0,
        "il_ID": 17,
        "il_ADI": null,
        "secim_DETAY_ID": 0
    },
    {
        "muhtarlik_ID": 72837,
        "min_SANDIK_NO": "1081",
        "max_SANDIK_NO": "1081",
        "muhtarlik_ADI": "DEMİRTEPE KÖYÜ",
        "cezaevi_ID": 0,
        "id": "237_0_1360",
        "birim_ID": 1360,
        "ilce_ID": 237,
        "ilce_ADI": null,
        "belde_ID": 0,
        "secim_CEVRESI_ID": 0,
        "yerlesim_YERI_TURU": 0,
        "secilecek_ADAY_SAYISI": 0,
        "il_ID": 17,
        "il_ADI": null,
        "secim_DETAY_ID": 0
    },
    {
        "muhtarlik_ID": 74342,
        "min_SANDIK_NO": "1062",
        "max_SANDIK_NO": "1063",
        "muhtarlik_ADI": "EVREŞE-ÇEŞME MAH.",
        "cezaevi_ID": 0,
        "id": "237_0_1360",
        "birim_ID": 1360,
        "ilce_ID": 237,
        "ilce_ADI": null,
        "belde_ID": 0,
        "secim_CEVRESI_ID": 0,
        "yerlesim_YERI_TURU": 0,
        "secilecek_ADAY_SAYISI": 0,
        "il_ID": 17,
        "il_ADI": null,
        "secim_DETAY_ID": 0
    },
    {
        "muhtarlik_ID": 74340,
        "min_SANDIK_NO": "1064",
        "max_SANDIK_NO": "1064",
        "muhtarlik_ADI": "EVREŞE-KEŞANOĞLU MAH.",
        "cezaevi_ID": 0,
        "id": "237_0_1360",
        "birim_ID": 1360,
        "ilce_ID": 237,
        "ilce_ADI": null,
        "belde_ID": 0,
        "secim_CEVRESI_ID": 0,
        "yerlesim_YERI_TURU": 0,
        "secilecek_ADAY_SAYISI": 0,
        "il_ID": 17,
        "il_ADI": null,
        "secim_DETAY_ID": 0
    },
    {
        "muhtarlik_ID": 74341,
        "min_SANDIK_NO": "1065",
        "max_SANDIK_NO": "1066",
        "muhtarlik_ADI": "EVREŞE-YENİ MAH.",
        "cezaevi_ID": 0,
        "id": "237_0_1360",
        "birim_ID": 1360,
        "ilce_ID": 237,
        "ilce_ADI": null,
        "belde_ID": 0,
        "secim_CEVRESI_ID": 0,
        "yerlesim_YERI_TURU": 0,
        "secilecek_ADAY_SAYISI": 0,
        "il_ID": 17,
        "il_ADI": null,
        "secim_DETAY_ID": 0
    },
    {
        "muhtarlik_ID": 87193,
        "min_SANDIK_NO": "1082",
        "max_SANDIK_NO": "1082",
        "muhtarlik_ADI": "FINDIKLI KÖYÜ",
        "cezaevi_ID": 0,
        "id": "237_0_1360",
        "birim_ID": 1360,
        "ilce_ID": 237,
        "ilce_ADI": null,
        "belde_ID": 0,
        "secim_CEVRESI_ID": 0,
        "yerlesim_YERI_TURU": 0,
        "secilecek_ADAY_SAYISI": 0,
        "il_ID": 17,
        "il_ADI": null,
        "secim_DETAY_ID": 0
    },
    {
        "muhtarlik_ID": 87185,
        "min_SANDIK_NO": "1025",
        "max_SANDIK_NO": "1034",
        "muhtarlik_ADI": "GAZİ SÜLEYMAN PAŞA MAH.",
        "cezaevi_ID": 0,
        "id": "237_0_1360",
        "birim_ID": 1360,
        "ilce_ID": 237,
        "ilce_ADI": null,
        "belde_ID": 0,
        "secim_CEVRESI_ID": 0,
        "yerlesim_YERI_TURU": 0,
        "secilecek_ADAY_SAYISI": 0,
        "il_ID": 17,
        "il_ADI": null,
        "secim_DETAY_ID": 0
    },
    {
        "muhtarlik_ID": 72838,
        "min_SANDIK_NO": "1083",
        "max_SANDIK_NO": "1084",
        "muhtarlik_ADI": "GÜNEYLİ KÖYÜ",
        "cezaevi_ID": 0,
        "id": "237_0_1360",
        "birim_ID": 1360,
        "ilce_ID": 237,
        "ilce_ADI": null,
        "belde_ID": 0,
        "secim_CEVRESI_ID": 0,
        "yerlesim_YERI_TURU": 0,
        "secilecek_ADAY_SAYISI": 0,
        "il_ID": 17,
        "il_ADI": null,
        "secim_DETAY_ID": 0
    },
    {
        "muhtarlik_ID": 87186,
        "min_SANDIK_NO": "1035",
        "max_SANDIK_NO": "1040",
        "muhtarlik_ADI": "HOCA HAMZA MAH.",
        "cezaevi_ID": 0,
        "id": "237_0_1360",
        "birim_ID": 1360,
        "ilce_ID": 237,
        "ilce_ADI": null,
        "belde_ID": 0,
        "secim_CEVRESI_ID": 0,
        "yerlesim_YERI_TURU": 0,
        "secilecek_ADAY_SAYISI": 0,
        "il_ID": 17,
        "il_ADI": null,
        "secim_DETAY_ID": 0
    },
    {
        "muhtarlik_ID": 87194,
        "min_SANDIK_NO": "1085",
        "max_SANDIK_NO": "1085",
        "muhtarlik_ADI": "ILGARDERE KÖYÜ",
        "cezaevi_ID": 0,
        "id": "237_0_1360",
        "birim_ID": 1360,
        "ilce_ID": 237,
        "ilce_ADI": null,
        "belde_ID": 0,
        "secim_CEVRESI_ID": 0,
        "yerlesim_YERI_TURU": 0,
        "secilecek_ADAY_SAYISI": 0,
        "il_ID": 17,
        "il_ADI": null,
        "secim_DETAY_ID": 0
    },
    {
        "muhtarlik_ID": 74346,
        "min_SANDIK_NO": "1086",
        "max_SANDIK_NO": "1086",
        "muhtarlik_ADI": "KALEALTI KÖYÜ",
        "cezaevi_ID": 0,
        "id": "237_0_1360",
        "birim_ID": 1360,
        "ilce_ID": 237,
        "ilce_ADI": null,
        "belde_ID": 0,
        "secim_CEVRESI_ID": 0,
        "yerlesim_YERI_TURU": 0,
        "secilecek_ADAY_SAYISI": 0,
        "il_ID": 17,
        "il_ADI": null,
        "secim_DETAY_ID": 0
    },
    {
        "muhtarlik_ID": 87195,
        "min_SANDIK_NO": "1087",
        "max_SANDIK_NO": "1087",
        "muhtarlik_ADI": "KARAİNEBEYLİ KÖYÜ",
        "cezaevi_ID": 0,
        "id": "237_0_1360",
        "birim_ID": 1360,
        "ilce_ID": 237,
        "ilce_ADI": null,
        "belde_ID": 0,
        "secim_CEVRESI_ID": 0,
        "yerlesim_YERI_TURU": 0,
        "secilecek_ADAY_SAYISI": 0,
        "il_ID": 17,
        "il_ADI": null,
        "secim_DETAY_ID": 0
    },
    {
        "muhtarlik_ID": 72839,
        "min_SANDIK_NO": "1067",
        "max_SANDIK_NO": "1067",
        "muhtarlik_ADI": "KAVAKKÖY-CUMHURİYET MAH.",
        "cezaevi_ID": 0,
        "id": "237_0_1360",
        "birim_ID": 1360,
        "ilce_ID": 237,
        "ilce_ADI": null,
        "belde_ID": 0,
        "secim_CEVRESI_ID": 0,
        "yerlesim_YERI_TURU": 0,
        "secilecek_ADAY_SAYISI": 0,
        "il_ID": 17,
        "il_ADI": null,
        "secim_DETAY_ID": 0
    },
    {
        "muhtarlik_ID": 72840,
        "min_SANDIK_NO": "1068",
        "max_SANDIK_NO": "1068",
        "muhtarlik_ADI": "KAVAKKÖY-HÜRRİYET MAH.",
        "cezaevi_ID": 0,
        "id": "237_0_1360",
        "birim_ID": 1360,
        "ilce_ID": 237,
        "ilce_ADI": null,
        "belde_ID": 0,
        "secim_CEVRESI_ID": 0,
        "yerlesim_YERI_TURU": 0,
        "secilecek_ADAY_SAYISI": 0,
        "il_ID": 17,
        "il_ADI": null,
        "secim_DETAY_ID": 0
    },
    {
        "muhtarlik_ID": 87196,
        "min_SANDIK_NO": "1088",
        "max_SANDIK_NO": "1088",
        "muhtarlik_ADI": "KAVAKLI KÖYÜ",
        "cezaevi_ID": 0,
        "id": "237_0_1360",
        "birim_ID": 1360,
        "ilce_ID": 237,
        "ilce_ADI": null,
        "belde_ID": 0,
        "secim_CEVRESI_ID": 0,
        "yerlesim_YERI_TURU": 0,
        "secilecek_ADAY_SAYISI": 0,
        "il_ID": 17,
        "il_ADI": null,
        "secim_DETAY_ID": 0
    },
    {
        "muhtarlik_ID": 74347,
        "min_SANDIK_NO": "1089",
        "max_SANDIK_NO": "1089",
        "muhtarlik_ADI": "KOCAÇEŞME KÖYÜ",
        "cezaevi_ID": 0,
        "id": "237_0_1360",
        "birim_ID": 1360,
        "ilce_ID": 237,
        "ilce_ADI": null,
        "belde_ID": 0,
        "secim_CEVRESI_ID": 0,
        "yerlesim_YERI_TURU": 0,
        "secilecek_ADAY_SAYISI": 0,
        "il_ID": 17,
        "il_ADI": null,
        "secim_DETAY_ID": 0
    },
    {
        "muhtarlik_ID": 72841,
        "min_SANDIK_NO": "1090",
        "max_SANDIK_NO": "1090",
        "muhtarlik_ADI": "KORUKÖY",
        "cezaevi_ID": 0,
        "id": "237_0_1360",
        "birim_ID": 1360,
        "ilce_ID": 237,
        "ilce_ADI": null,
        "belde_ID": 0,
        "secim_CEVRESI_ID": 0,
        "yerlesim_YERI_TURU": 0,
        "secilecek_ADAY_SAYISI": 0,
        "il_ID": 17,
        "il_ADI": null,
        "secim_DETAY_ID": 0
    },
    {
        "muhtarlik_ID": 87197,
        "min_SANDIK_NO": "1091",
        "max_SANDIK_NO": "1091",
        "muhtarlik_ADI": "OCAKLI KÖYÜ",
        "cezaevi_ID": 0,
        "id": "237_0_1360",
        "birim_ID": 1360,
        "ilce_ID": 237,
        "ilce_ADI": null,
        "belde_ID": 0,
        "secim_CEVRESI_ID": 0,
        "yerlesim_YERI_TURU": 0,
        "secilecek_ADAY_SAYISI": 0,
        "il_ID": 17,
        "il_ADI": null,
        "secim_DETAY_ID": 0
    },
    {
        "muhtarlik_ID": 87198,
        "min_SANDIK_NO": "1092",
        "max_SANDIK_NO": "1092",
        "muhtarlik_ADI": "PAZARLI KÖYÜ",
        "cezaevi_ID": 0,
        "id": "237_0_1360",
        "birim_ID": 1360,
        "ilce_ID": 237,
        "ilce_ADI": null,
        "belde_ID": 0,
        "secim_CEVRESI_ID": 0,
        "yerlesim_YERI_TURU": 0,
        "secilecek_ADAY_SAYISI": 0,
        "il_ID": 17,
        "il_ADI": null,
        "secim_DETAY_ID": 0
    },
    {
        "muhtarlik_ID": 74348,
        "min_SANDIK_NO": "1093",
        "max_SANDIK_NO": "1093",
        "muhtarlik_ADI": "SÜLEYMANİYE KÖYÜ",
        "cezaevi_ID": 0,
        "id": "237_0_1360",
        "birim_ID": 1360,
        "ilce_ID": 237,
        "ilce_ADI": null,
        "belde_ID": 0,
        "secim_CEVRESI_ID": 0,
        "yerlesim_YERI_TURU": 0,
        "secilecek_ADAY_SAYISI": 0,
        "il_ID": 17,
        "il_ADI": null,
        "secim_DETAY_ID": 0
    },
    {
        "muhtarlik_ID": 87199,
        "min_SANDIK_NO": "1094",
        "max_SANDIK_NO": "1095",
        "muhtarlik_ADI": "SÜTLÜCE KÖYÜ",
        "cezaevi_ID": 0,
        "id": "237_0_1360",
        "birim_ID": 1360,
        "ilce_ID": 237,
        "ilce_ADI": null,
        "belde_ID": 0,
        "secim_CEVRESI_ID": 0,
        "yerlesim_YERI_TURU": 0,
        "secilecek_ADAY_SAYISI": 0,
        "il_ID": 17,
        "il_ADI": null,
        "secim_DETAY_ID": 0
    },
    {
        "muhtarlik_ID": 74349,
        "min_SANDIK_NO": "1096",
        "max_SANDIK_NO": "1096",
        "muhtarlik_ADI": "ŞADILLI KÖYÜ",
        "cezaevi_ID": 0,
        "id": "237_0_1360",
        "birim_ID": 1360,
        "ilce_ID": 237,
        "ilce_ADI": null,
        "belde_ID": 0,
        "secim_CEVRESI_ID": 0,
        "yerlesim_YERI_TURU": 0,
        "secilecek_ADAY_SAYISI": 0,
        "il_ID": 17,
        "il_ADI": null,
        "secim_DETAY_ID": 0
    },
    {
        "muhtarlik_ID": 87200,
        "min_SANDIK_NO": "1097",
        "max_SANDIK_NO": "1098",
        "muhtarlik_ADI": "TAYFURKÖY",
        "cezaevi_ID": 0,
        "id": "237_0_1360",
        "birim_ID": 1360,
        "ilce_ID": 237,
        "ilce_ADI": null,
        "belde_ID": 0,
        "secim_CEVRESI_ID": 0,
        "yerlesim_YERI_TURU": 0,
        "secilecek_ADAY_SAYISI": 0,
        "il_ID": 17,
        "il_ADI": null,
        "secim_DETAY_ID": 0
    },
    {
        "muhtarlik_ID": 87187,
        "min_SANDIK_NO": "1041",
        "max_SANDIK_NO": "1057",
        "muhtarlik_ADI": "YAZICIZADE MAH.",
        "cezaevi_ID": 0,
        "id": "237_0_1360",
        "birim_ID": 1360,
        "ilce_ID": 237,
        "ilce_ADI": null,
        "belde_ID": 0,
        "secim_CEVRESI_ID": 0,
        "yerlesim_YERI_TURU": 0,
        "secilecek_ADAY_SAYISI": 0,
        "il_ID": 17,
        "il_ADI": null,
        "secim_DETAY_ID": 0
    },
    {
        "muhtarlik_ID": 87201,
        "min_SANDIK_NO": "1099",
        "max_SANDIK_NO": "1100",
        "muhtarlik_ADI": "YENİKÖY",
        "cezaevi_ID": 0,
        "id": "237_0_1360",
        "birim_ID": 1360,
        "ilce_ID": 237,
        "ilce_ADI": null,
        "belde_ID": 0,
        "secim_CEVRESI_ID": 0,
        "yerlesim_YERI_TURU": 0,
        "secilecek_ADAY_SAYISI": 0,
        "il_ID": 17,
        "il_ADI": null,
        "secim_DETAY_ID": 0
    },
    {
        "muhtarlik_ID": 74350,
        "min_SANDIK_NO": "1101",
        "max_SANDIK_NO": "1102",
        "muhtarlik_ADI": "YÜLÜCE KÖYÜ",
        "cezaevi_ID": 0,
        "id": "237_0_1360",
        "birim_ID": 1360,
        "ilce_ID": 237,
        "ilce_ADI": null,
        "belde_ID": 0,
        "secim_CEVRESI_ID": 0,
        "yerlesim_YERI_TURU": 0,
        "secilecek_ADAY_SAYISI": 0,
        "il_ID": 17,
        "il_ADI": null,
        "secim_DETAY_ID": 0
    }
]