[
    {
        "muhtarlik_ID": 104756,
        "min_SANDIK_NO": "1205",
        "max_SANDIK_NO": "1205",
        "muhtarlik_ADI": "AKALIN KÖYÜ",
        "cezaevi_ID": 0,
        "id": "368_0_1736",
        "birim_ID": 1736,
        "ilce_ID": 368,
        "ilce_ADI": null,
        "belde_ID": 0,
        "secim_CEVRESI_ID": 0,
        "yerlesim_YERI_TURU": 0,
        "secilecek_ADAY_SAYISI": 0,
        "il_ID": 47,
        "il_ADI": null,
        "secim_DETAY_ID": 0
    },
    {
        "muhtarlik_ID": 104757,
        "min_SANDIK_NO": "1206",
        "max_SANDIK_NO": "1206",
        "muhtarlik_ADI": "AKÇA KÖYÜ",
        "cezaevi_ID": 0,
        "id": "368_0_1736",
        "birim_ID": 1736,
        "ilce_ID": 368,
        "ilce_ADI": null,
        "belde_ID": 0,
        "secim_CEVRESI_ID": 0,
        "yerlesim_YERI_TURU": 0,
        "secilecek_ADAY_SAYISI": 0,
        "il_ID": 47,
        "il_ADI": null,
        "secim_DETAY_ID": 0
    },
    {
        "muhtarlik_ID": 104758,
        "min_SANDIK_NO": "1207",
        "max_SANDIK_NO": "1207",
        "muhtarlik_ADI": "AKÇAPINAR KÖYÜ",
        "cezaevi_ID": 0,
        "id": "368_0_1736",
        "birim_ID": 1736,
        "ilce_ID": 368,
        "ilce_ADI": null,
        "belde_ID": 0,
        "secim_CEVRESI_ID": 0,
        "yerlesim_YERI_TURU": 0,
        "secilecek_ADAY_SAYISI": 0,
        "il_ID": 47,
        "il_ADI": null,
        "secim_DETAY_ID": 0
    },
    {
        "muhtarlik_ID": 104759,
        "min_SANDIK_NO": "1208",
        "max_SANDIK_NO": "1208",
        "muhtarlik_ADI": "AKDOĞAN KÖYÜ",
        "cezaevi_ID": 0,
        "id": "368_0_1736",
        "birim_ID": 1736,
        "ilce_ID": 368,
        "ilce_ADI": null,
        "belde_ID": 0,
        "secim_CEVRESI_ID": 0,
        "yerlesim_YERI_TURU": 0,
        "secilecek_ADAY_SAYISI": 0,
        "il_ID": 47,
        "il_ADI": null,
        "secim_DETAY_ID": 0
    },
    {
        "muhtarlik_ID": 104760,
        "min_SANDIK_NO": "1209",
        "max_SANDIK_NO": "1209",
        "muhtarlik_ADI": "AKKOÇ KÖYÜ",
        "cezaevi_ID": 0,
        "id": "368_0_1736",
        "birim_ID": 1736,
        "ilce_ID": 368,
        "ilce_ADI": null,
        "belde_ID": 0,
        "secim_CEVRESI_ID": 0,
        "yerlesim_YERI_TURU": 0,
        "secilecek_ADAY_SAYISI": 0,
        "il_ID": 47,
        "il_ADI": null,
        "secim_DETAY_ID": 0
    },
    {
        "muhtarlik_ID": 104886,
        "min_SANDIK_NO": "1210",
        "max_SANDIK_NO": "1210",
        "muhtarlik_ADI": "AKTEPE KÖYÜ",
        "cezaevi_ID": 0,
        "id": "368_0_1736",
        "birim_ID": 1736,
        "ilce_ID": 368,
        "ilce_ADI": null,
        "belde_ID": 0,
        "secim_CEVRESI_ID": 0,
        "yerlesim_YERI_TURU": 0,
        "secilecek_ADAY_SAYISI": 0,
        "il_ID": 47,
        "il_ADI": null,
        "secim_DETAY_ID": 0
    },
    {
        "muhtarlik_ID": 104761,
        "min_SANDIK_NO": "1211",
        "max_SANDIK_NO": "1211",
        "muhtarlik_ADI": "AKTULGA KÖYÜ",
        "cezaevi_ID": 0,
        "id": "368_0_1736",
        "birim_ID": 1736,
        "ilce_ID": 368,
        "ilce_ADI": null,
        "belde_ID": 0,
        "secim_CEVRESI_ID": 0,
        "yerlesim_YERI_TURU": 0,
        "secilecek_ADAY_SAYISI": 0,
        "il_ID": 47,
        "il_ADI": null,
        "secim_DETAY_ID": 0
    },
    {
        "muhtarlik_ID": 104762,
        "min_SANDIK_NO": "1212",
        "max_SANDIK_NO": "1213",
        "muhtarlik_ADI": "AKYAZI KÖYÜ",
        "cezaevi_ID": 0,
        "id": "368_0_1736",
        "birim_ID": 1736,
        "ilce_ID": 368,
        "ilce_ADI": null,
        "belde_ID": 0,
        "secim_CEVRESI_ID": 0,
        "yerlesim_YERI_TURU": 0,
        "secilecek_ADAY_SAYISI": 0,
        "il_ID": 47,
        "il_ADI": null,
        "secim_DETAY_ID": 0
    },
    {
        "muhtarlik_ID": 124765,
        "min_SANDIK_NO": "1214",
        "max_SANDIK_NO": "1214",
        "muhtarlik_ADI": "AKYÜZ KÖYÜ",
        "cezaevi_ID": 0,
        "id": "368_0_1736",
        "birim_ID": 1736,
        "ilce_ID": 368,
        "ilce_ADI": null,
        "belde_ID": 0,
        "secim_CEVRESI_ID": 0,
        "yerlesim_YERI_TURU": 0,
        "secilecek_ADAY_SAYISI": 0,
        "il_ID": 47,
        "il_ADI": null,
        "secim_DETAY_ID": 0
    },
    {
        "muhtarlik_ID": 104763,
        "min_SANDIK_NO": "1215",
        "max_SANDIK_NO": "1215",
        "muhtarlik_ADI": "AKZİYARET KÖYÜ",
        "cezaevi_ID": 0,
        "id": "368_0_1736",
        "birim_ID": 1736,
        "ilce_ID": 368,
        "ilce_ADI": null,
        "belde_ID": 0,
        "secim_CEVRESI_ID": 0,
        "yerlesim_YERI_TURU": 0,
        "secilecek_ADAY_SAYISI": 0,
        "il_ID": 47,
        "il_ADI": null,
        "secim_DETAY_ID": 0
    },
    {
        "muhtarlik_ID": 104764,
        "min_SANDIK_NO": "1216",
        "max_SANDIK_NO": "1216",
        "muhtarlik_ADI": "ALAKUŞ KÖYÜ",
        "cezaevi_ID": 0,
        "id": "368_0_1736",
        "birim_ID": 1736,
        "ilce_ID": 368,
        "ilce_ADI": null,
        "belde_ID": 0,
        "secim_CEVRESI_ID": 0,
        "yerlesim_YERI_TURU": 0,
        "secilecek_ADAY_SAYISI": 0,
        "il_ID": 47,
        "il_ADI": null,
        "secim_DETAY_ID": 0
    },
    {
        "muhtarlik_ID": 124766,
        "min_SANDIK_NO": "1217",
        "max_SANDIK_NO": "1217",
        "muhtarlik_ADI": "ALEMDAR KÖYÜ",
        "cezaevi_ID": 0,
        "id": "368_0_1736",
        "birim_ID": 1736,
        "ilce_ID": 368,
        "ilce_ADI": null,
        "belde_ID": 0,
        "secim_CEVRESI_ID": 0,
        "yerlesim_YERI_TURU": 0,
        "secilecek_ADAY_SAYISI": 0,
        "il_ID": 47,
        "il_ADI": null,
        "secim_DETAY_ID": 0
    },
    {
        "muhtarlik_ID": 104765,
        "min_SANDIK_NO": "1218",
        "max_SANDIK_NO": "1218",
        "muhtarlik_ADI": "ALİPAŞA KÖYÜ",
        "cezaevi_ID": 0,
        "id": "368_0_1736",
        "birim_ID": 1736,
        "ilce_ID": 368,
        "ilce_ADI": null,
        "belde_ID": 0,
        "secim_CEVRESI_ID": 0,
        "yerlesim_YERI_TURU": 0,
        "secilecek_ADAY_SAYISI": 0,
        "il_ID": 47,
        "il_ADI": null,
        "secim_DETAY_ID": 0
    },
    {
        "muhtarlik_ID": 124767,
        "min_SANDIK_NO": "1219",
        "max_SANDIK_NO": "1219",
        "muhtarlik_ADI": "ALTINTOPRAK KÖYÜ",
        "cezaevi_ID": 0,
        "id": "368_0_1736",
        "birim_ID": 1736,
        "ilce_ID": 368,
        "ilce_ADI": null,
        "belde_ID": 0,
        "secim_CEVRESI_ID": 0,
        "yerlesim_YERI_TURU": 0,
        "secilecek_ADAY_SAYISI": 0,
        "il_ID": 47,
        "il_ADI": null,
        "secim_DETAY_ID": 0
    },
    {
        "muhtarlik_ID": 104766,
        "min_SANDIK_NO": "1220",
        "max_SANDIK_NO": "1220",
        "muhtarlik_ADI": "ARAKAPI KÖYÜ",
        "cezaevi_ID": 0,
        "id": "368_0_1736",
        "birim_ID": 1736,
        "ilce_ID": 368,
        "ilce_ADI": null,
        "belde_ID": 0,
        "secim_CEVRESI_ID": 0,
        "yerlesim_YERI_TURU": 0,
        "secilecek_ADAY_SAYISI": 0,
        "il_ID": 47,
        "il_ADI": null,
        "secim_DETAY_ID": 0
    },
    {
        "muhtarlik_ID": 104767,
        "min_SANDIK_NO": "1221",
        "max_SANDIK_NO": "1221",
        "muhtarlik_ADI": "ARAKÖY",
        "cezaevi_ID": 0,
        "id": "368_0_1736",
        "birim_ID": 1736,
        "ilce_ID": 368,
        "ilce_ADI": null,
        "belde_ID": 0,
        "secim_CEVRESI_ID": 0,
        "yerlesim_YERI_TURU": 0,
        "secilecek_ADAY_SAYISI": 0,
        "il_ID": 47,
        "il_ADI": null,
        "secim_DETAY_ID": 0
    },
    {
        "muhtarlik_ID": 104768,
        "min_SANDIK_NO": "1222",
        "max_SANDIK_NO": "1226",
        "muhtarlik_ADI": "ARIKLI KÖYÜ",
        "cezaevi_ID": 0,
        "id": "368_0_1736",
        "birim_ID": 1736,
        "ilce_ID": 368,
        "ilce_ADI": null,
        "belde_ID": 0,
        "secim_CEVRESI_ID": 0,
        "yerlesim_YERI_TURU": 0,
        "secilecek_ADAY_SAYISI": 0,
        "il_ID": 47,
        "il_ADI": null,
        "secim_DETAY_ID": 0
    },
    {
        "muhtarlik_ID": 104769,
        "min_SANDIK_NO": "1227",
        "max_SANDIK_NO": "1227",
        "muhtarlik_ADI": "ARITEPE KÖYÜ",
        "cezaevi_ID": 0,
        "id": "368_0_1736",
        "birim_ID": 1736,
        "ilce_ID": 368,
        "ilce_ADI": null,
        "belde_ID": 0,
        "secim_CEVRESI_ID": 0,
        "yerlesim_YERI_TURU": 0,
        "secilecek_ADAY_SAYISI": 0,
        "il_ID": 47,
        "il_ADI": null,
        "secim_DETAY_ID": 0
    },
    {
        "muhtarlik_ID": 104770,
        "min_SANDIK_NO": "1228",
        "max_SANDIK_NO": "1228",
        "muhtarlik_ADI": "ASLANLI KÖYÜ",
        "cezaevi_ID": 0,
        "id": "368_0_1736",
        "birim_ID": 1736,
        "ilce_ID": 368,
        "ilce_ADI": null,
        "belde_ID": 0,
        "secim_CEVRESI_ID": 0,
        "yerlesim_YERI_TURU": 0,
        "secilecek_ADAY_SAYISI": 0,
        "il_ID": 47,
        "il_ADI": null,
        "secim_DETAY_ID": 0
    },
    {
        "muhtarlik_ID": 104771,
        "min_SANDIK_NO": "1229",
        "max_SANDIK_NO": "1229",
        "muhtarlik_ADI": "AŞAĞIAZIKLI KÖYÜ",
        "cezaevi_ID": 0,
        "id": "368_0_1736",
        "birim_ID": 1736,
        "ilce_ID": 368,
        "ilce_ADI": null,
        "belde_ID": 0,
        "secim_CEVRESI_ID": 0,
        "yerlesim_YERI_TURU": 0,
        "secilecek_ADAY_SAYISI": 0,
        "il_ID": 47,
        "il_ADI": null,
        "secim_DETAY_ID": 0
    },
    {
        "muhtarlik_ID": 124768,
        "min_SANDIK_NO": "1230",
        "max_SANDIK_NO": "1230",
        "muhtarlik_ADI": "ATAKÖY",
        "cezaevi_ID": 0,
        "id": "368_0_1736",
        "birim_ID": 1736,
        "ilce_ID": 368,
        "ilce_ADI": null,
        "belde_ID": 0,
        "secim_CEVRESI_ID": 0,
        "yerlesim_YERI_TURU": 0,
        "secilecek_ADAY_SAYISI": 0,
        "il_ID": 47,
        "il_ADI": null,
        "secim_DETAY_ID": 0
    },
    {
        "muhtarlik_ID": 104746,
        "min_SANDIK_NO": "1001",
        "max_SANDIK_NO": "1014",
        "muhtarlik_ADI": "ATATÜRK MAH.",
        "cezaevi_ID": 0,
        "id": "368_0_1736",
        "birim_ID": 1736,
        "ilce_ID": 368,
        "ilce_ADI": null,
        "belde_ID": 0,
        "secim_CEVRESI_ID": 0,
        "yerlesim_YERI_TURU": 0,
        "secilecek_ADAY_SAYISI": 0,
        "il_ID": 47,
        "il_ADI": null,
        "secim_DETAY_ID": 0
    },
    {
        "muhtarlik_ID": 104772,
        "min_SANDIK_NO": "1231",
        "max_SANDIK_NO": "1231",
        "muhtarlik_ADI": "ATMACA KÖYÜ",
        "cezaevi_ID": 0,
        "id": "368_0_1736",
        "birim_ID": 1736,
        "ilce_ID": 368,
        "ilce_ADI": null,
        "belde_ID": 0,
        "secim_CEVRESI_ID": 0,
        "yerlesim_YERI_TURU": 0,
        "secilecek_ADAY_SAYISI": 0,
        "il_ID": 47,
        "il_ADI": null,
        "secim_DETAY_ID": 0
    },
    {
        "muhtarlik_ID": 104773,
        "min_SANDIK_NO": "1232",
        "max_SANDIK_NO": "1232",
        "muhtarlik_ADI": "AYAZ KÖYÜ",
        "cezaevi_ID": 0,
        "id": "368_0_1736",
        "birim_ID": 1736,
        "ilce_ID": 368,
        "ilce_ADI": null,
        "belde_ID": 0,
        "secim_CEVRESI_ID": 0,
        "yerlesim_YERI_TURU": 0,
        "secilecek_ADAY_SAYISI": 0,
        "il_ID": 47,
        "il_ADI": null,
        "secim_DETAY_ID": 0
    },
    {
        "muhtarlik_ID": 104774,
        "min_SANDIK_NO": "1233",
        "max_SANDIK_NO": "1234",
        "muhtarlik_ADI": "BAĞRIBÜTÜN KÖYÜ",
        "cezaevi_ID": 0,
        "id": "368_0_1736",
        "birim_ID": 1736,
        "ilce_ID": 368,
        "ilce_ADI": null,
        "belde_ID": 0,
        "secim_CEVRESI_ID": 0,
        "yerlesim_YERI_TURU": 0,
        "secilecek_ADAY_SAYISI": 0,
        "il_ID": 47,
        "il_ADI": null,
        "secim_DETAY_ID": 0
    },
    {
        "muhtarlik_ID": 104747,
        "min_SANDIK_NO": "1015",
        "max_SANDIK_NO": "1027",
        "muhtarlik_ADI": "BAHÇELİEVLER MAH.",
        "cezaevi_ID": 0,
        "id": "368_0_1736",
        "birim_ID": 1736,
        "ilce_ID": 368,
        "ilce_ADI": null,
        "belde_ID": 0,
        "secim_CEVRESI_ID": 0,
        "yerlesim_YERI_TURU": 0,
        "secilecek_ADAY_SAYISI": 0,
        "il_ID": 47,
        "il_ADI": null,
        "secim_DETAY_ID": 0
    },
    {
        "muhtarlik_ID": 104775,
        "min_SANDIK_NO": "1235",
        "max_SANDIK_NO": "1235",
        "muhtarlik_ADI": "BARIŞ KÖYÜ",
        "cezaevi_ID": 0,
        "id": "368_0_1736",
        "birim_ID": 1736,
        "ilce_ID": 368,
        "ilce_ADI": null,
        "belde_ID": 0,
        "secim_CEVRESI_ID": 0,
        "yerlesim_YERI_TURU": 0,
        "secilecek_ADAY_SAYISI": 0,
        "il_ID": 47,
        "il_ADI": null,
        "secim_DETAY_ID": 0
    },
    {
        "muhtarlik_ID": 104776,
        "min_SANDIK_NO": "1236",
        "max_SANDIK_NO": "1237",
        "muhtarlik_ADI": "BAŞAK KÖYÜ",
        "cezaevi_ID": 0,
        "id": "368_0_1736",
        "birim_ID": 1736,
        "ilce_ID": 368,
        "ilce_ADI": null,
        "belde_ID": 0,
        "secim_CEVRESI_ID": 0,
        "yerlesim_YERI_TURU": 0,
        "secilecek_ADAY_SAYISI": 0,
        "il_ID": 47,
        "il_ADI": null,
        "secim_DETAY_ID": 0
    },
    {
        "muhtarlik_ID": 104778,
        "min_SANDIK_NO": "1238",
        "max_SANDIK_NO": "1238",
        "muhtarlik_ADI": "BEKTAŞ KÖYÜ",
        "cezaevi_ID": 0,
        "id": "368_0_1736",
        "birim_ID": 1736,
        "ilce_ID": 368,
        "ilce_ADI": null,
        "belde_ID": 0,
        "secim_CEVRESI_ID": 0,
        "yerlesim_YERI_TURU": 0,
        "secilecek_ADAY_SAYISI": 0,
        "il_ID": 47,
        "il_ADI": null,
        "secim_DETAY_ID": 0
    },
    {
        "muhtarlik_ID": 104779,
        "min_SANDIK_NO": "1239",
        "max_SANDIK_NO": "1239",
        "muhtarlik_ADI": "BELLİ KÖYÜ",
        "cezaevi_ID": 0,
        "id": "368_0_1736",
        "birim_ID": 1736,
        "ilce_ID": 368,
        "ilce_ADI": null,
        "belde_ID": 0,
        "secim_CEVRESI_ID": 0,
        "yerlesim_YERI_TURU": 0,
        "secilecek_ADAY_SAYISI": 0,
        "il_ID": 47,
        "il_ADI": null,
        "secim_DETAY_ID": 0
    },
    {
        "muhtarlik_ID": 104777,
        "min_SANDIK_NO": "1240",
        "max_SANDIK_NO": "1240",
        "muhtarlik_ADI": "BEŞDEĞİRMEN KÖYÜ",
        "cezaevi_ID": 0,
        "id": "368_0_1736",
        "birim_ID": 1736,
        "ilce_ID": 368,
        "ilce_ADI": null,
        "belde_ID": 0,
        "secim_CEVRESI_ID": 0,
        "yerlesim_YERI_TURU": 0,
        "secilecek_ADAY_SAYISI": 0,
        "il_ID": 47,
        "il_ADI": null,
        "secim_DETAY_ID": 0
    },
    {
        "muhtarlik_ID": 104888,
        "min_SANDIK_NO": "1241",
        "max_SANDIK_NO": "1241",
        "muhtarlik_ADI": "BEŞEVLER KÖYÜ",
        "cezaevi_ID": 0,
        "id": "368_0_1736",
        "birim_ID": 1736,
        "ilce_ID": 368,
        "ilce_ADI": null,
        "belde_ID": 0,
        "secim_CEVRESI_ID": 0,
        "yerlesim_YERI_TURU": 0,
        "secilecek_ADAY_SAYISI": 0,
        "il_ID": 47,
        "il_ADI": null,
        "secim_DETAY_ID": 0
    },
    {
        "muhtarlik_ID": 104890,
        "min_SANDIK_NO": "1242",
        "max_SANDIK_NO": "1242",
        "muhtarlik_ADI": "BEŞİK KÖYÜ",
        "cezaevi_ID": 0,
        "id": "368_0_1736",
        "birim_ID": 1736,
        "ilce_ID": 368,
        "ilce_ADI": null,
        "belde_ID": 0,
        "secim_CEVRESI_ID": 0,
        "yerlesim_YERI_TURU": 0,
        "secilecek_ADAY_SAYISI": 0,
        "il_ID": 47,
        "il_ADI": null,
        "secim_DETAY_ID": 0
    },
    {
        "muhtarlik_ID": 104780,
        "min_SANDIK_NO": "1243",
        "max_SANDIK_NO": "1244",
        "muhtarlik_ADI": "BOZHÖYÜK KÖYÜ",
        "cezaevi_ID": 0,
        "id": "368_0_1736",
        "birim_ID": 1736,
        "ilce_ID": 368,
        "ilce_ADI": null,
        "belde_ID": 0,
        "secim_CEVRESI_ID": 0,
        "yerlesim_YERI_TURU": 0,
        "secilecek_ADAY_SAYISI": 0,
        "il_ID": 47,
        "il_ADI": null,
        "secim_DETAY_ID": 0
    },
    {
        "muhtarlik_ID": 104781,
        "min_SANDIK_NO": "1245",
        "max_SANDIK_NO": "1245",
        "muhtarlik_ADI": "BÜYÜKAYRIK KÖYÜ",
        "cezaevi_ID": 0,
        "id": "368_0_1736",
        "birim_ID": 1736,
        "ilce_ID": 368,
        "ilce_ADI": null,
        "belde_ID": 0,
        "secim_CEVRESI_ID": 0,
        "yerlesim_YERI_TURU": 0,
        "secilecek_ADAY_SAYISI": 0,
        "il_ID": 47,
        "il_ADI": null,
        "secim_DETAY_ID": 0
    },
    {
        "muhtarlik_ID": 104782,
        "min_SANDIK_NO": "1246",
        "max_SANDIK_NO": "1247",
        "muhtarlik_ADI": "BÜYÜKBOĞAZİYE KÖYÜ",
        "cezaevi_ID": 0,
        "id": "368_0_1736",
        "birim_ID": 1736,
        "ilce_ID": 368,
        "ilce_ADI": null,
        "belde_ID": 0,
        "secim_CEVRESI_ID": 0,
        "yerlesim_YERI_TURU": 0,
        "secilecek_ADAY_SAYISI": 0,
        "il_ID": 47,
        "il_ADI": null,
        "secim_DETAY_ID": 0
    },
    {
        "muhtarlik_ID": 104783,
        "min_SANDIK_NO": "1248",
        "max_SANDIK_NO": "1248",
        "muhtarlik_ADI": "BÜYÜKDERE KÖYÜ",
        "cezaevi_ID": 0,
        "id": "368_0_1736",
        "birim_ID": 1736,
        "ilce_ID": 368,
        "ilce_ADI": null,
        "belde_ID": 0,
        "secim_CEVRESI_ID": 0,
        "yerlesim_YERI_TURU": 0,
        "secilecek_ADAY_SAYISI": 0,
        "il_ID": 47,
        "il_ADI": null,
        "secim_DETAY_ID": 0
    },
    {
        "muhtarlik_ID": 104784,
        "min_SANDIK_NO": "1249",
        "max_SANDIK_NO": "1249",
        "muhtarlik_ADI": "BÜYÜKTEPE KÖYÜ",
        "cezaevi_ID": 0,
        "id": "368_0_1736",
        "birim_ID": 1736,
        "ilce_ID": 368,
        "ilce_ADI": null,
        "belde_ID": 0,
        "secim_CEVRESI_ID": 0,
        "yerlesim_YERI_TURU": 0,
        "secilecek_ADAY_SAYISI": 0,
        "il_ID": 47,
        "il_ADI": null,
        "secim_DETAY_ID": 0
    },
    {
        "muhtarlik_ID": 104785,
        "min_SANDIK_NO": "1250",
        "max_SANDIK_NO": "1250",
        "muhtarlik_ADI": "CANTAŞI KÖYÜ",
        "cezaevi_ID": 0,
        "id": "368_0_1736",
        "birim_ID": 1736,
        "ilce_ID": 368,
        "ilce_ADI": null,
        "belde_ID": 0,
        "secim_CEVRESI_ID": 0,
        "yerlesim_YERI_TURU": 0,
        "secilecek_ADAY_SAYISI": 0,
        "il_ID": 47,
        "il_ADI": null,
        "secim_DETAY_ID": 0
    },
    {
        "muhtarlik_ID": 104748,
        "min_SANDIK_NO": "1028",
        "max_SANDIK_NO": "1043",
        "muhtarlik_ADI": "CUMHURİYET MAH.",
        "cezaevi_ID": 0,
        "id": "368_0_1736",
        "birim_ID": 1736,
        "ilce_ID": 368,
        "ilce_ADI": null,
        "belde_ID": 0,
        "secim_CEVRESI_ID": 0,
        "yerlesim_YERI_TURU": 0,
        "secilecek_ADAY_SAYISI": 0,
        "il_ID": 47,
        "il_ADI": null,
        "secim_DETAY_ID": 0
    },
    {
        "muhtarlik_ID": 124769,
        "min_SANDIK_NO": "1251",
        "max_SANDIK_NO": "1251",
        "muhtarlik_ADI": "ÇAĞIL KÖYÜ",
        "cezaevi_ID": 0,
        "id": "368_0_1736",
        "birim_ID": 1736,
        "ilce_ID": 368,
        "ilce_ADI": null,
        "belde_ID": 0,
        "secim_CEVRESI_ID": 0,
        "yerlesim_YERI_TURU": 0,
        "secilecek_ADAY_SAYISI": 0,
        "il_ID": 47,
        "il_ADI": null,
        "secim_DETAY_ID": 0
    },
    {
        "muhtarlik_ID": 104786,
        "min_SANDIK_NO": "1252",
        "max_SANDIK_NO": "1252",
        "muhtarlik_ADI": "ÇAKIR KÖYÜ",
        "cezaevi_ID": 0,
        "id": "368_0_1736",
        "birim_ID": 1736,
        "ilce_ID": 368,
        "ilce_ADI": null,
        "belde_ID": 0,
        "secim_CEVRESI_ID": 0,
        "yerlesim_YERI_TURU": 0,
        "secilecek_ADAY_SAYISI": 0,
        "il_ID": 47,
        "il_ADI": null,
        "secim_DETAY_ID": 0
    },
    {
        "muhtarlik_ID": 104878,
        "min_SANDIK_NO": "1253",
        "max_SANDIK_NO": "1253",
        "muhtarlik_ADI": "ÇAMLICA KÖYÜ",
        "cezaevi_ID": 0,
        "id": "368_0_1736",
        "birim_ID": 1736,
        "ilce_ID": 368,
        "ilce_ADI": null,
        "belde_ID": 0,
        "secim_CEVRESI_ID": 0,
        "yerlesim_YERI_TURU": 0,
        "secilecek_ADAY_SAYISI": 0,
        "il_ID": 47,
        "il_ADI": null,
        "secim_DETAY_ID": 0
    },
    {
        "muhtarlik_ID": 124770,
        "min_SANDIK_NO": "1254",
        "max_SANDIK_NO": "1254",
        "muhtarlik_ADI": "ÇAMLIDERE KÖYÜ",
        "cezaevi_ID": 0,
        "id": "368_0_1736",
        "birim_ID": 1736,
        "ilce_ID": 368,
        "ilce_ADI": null,
        "belde_ID": 0,
        "secim_CEVRESI_ID": 0,
        "yerlesim_YERI_TURU": 0,
        "secilecek_ADAY_SAYISI": 0,
        "il_ID": 47,
        "il_ADI": null,
        "secim_DETAY_ID": 0
    },
    {
        "muhtarlik_ID": 104887,
        "min_SANDIK_NO": "1255",
        "max_SANDIK_NO": "1255",
        "muhtarlik_ADI": "ÇANAKLI KÖYÜ",
        "cezaevi_ID": 0,
        "id": "368_0_1736",
        "birim_ID": 1736,
        "ilce_ID": 368,
        "ilce_ADI": null,
        "belde_ID": 0,
        "secim_CEVRESI_ID": 0,
        "yerlesim_YERI_TURU": 0,
        "secilecek_ADAY_SAYISI": 0,
        "il_ID": 47,
        "il_ADI": null,
        "secim_DETAY_ID": 0
    },
    {
        "muhtarlik_ID": 104787,
        "min_SANDIK_NO": "1256",
        "max_SANDIK_NO": "1256",
        "muhtarlik_ADI": "ÇATALCA KÖYÜ",
        "cezaevi_ID": 0,
        "id": "368_0_1736",
        "birim_ID": 1736,
        "ilce_ID": 368,
        "ilce_ADI": null,
        "belde_ID": 0,
        "secim_CEVRESI_ID": 0,
        "yerlesim_YERI_TURU": 0,
        "secilecek_ADAY_SAYISI": 0,
        "il_ID": 47,
        "il_ADI": null,
        "secim_DETAY_ID": 0
    },
    {
        "muhtarlik_ID": 104891,
        "min_SANDIK_NO": "1257",
        "max_SANDIK_NO": "1257",
        "muhtarlik_ADI": "ÇAYBAŞI KÖYÜ",
        "cezaevi_ID": 0,
        "id": "368_0_1736",
        "birim_ID": 1736,
        "ilce_ID": 368,
        "ilce_ADI": null,
        "belde_ID": 0,
        "secim_CEVRESI_ID": 0,
        "yerlesim_YERI_TURU": 0,
        "secilecek_ADAY_SAYISI": 0,
        "il_ID": 47,
        "il_ADI": null,
        "secim_DETAY_ID": 0
    },
    {
        "muhtarlik_ID": 104788,
        "min_SANDIK_NO": "1258",
        "max_SANDIK_NO": "1258",
        "muhtarlik_ADI": "ÇETİNLER KÖYÜ",
        "cezaevi_ID": 0,
        "id": "368_0_1736",
        "birim_ID": 1736,
        "ilce_ID": 368,
        "ilce_ADI": null,
        "belde_ID": 0,
        "secim_CEVRESI_ID": 0,
        "yerlesim_YERI_TURU": 0,
        "secilecek_ADAY_SAYISI": 0,
        "il_ID": 47,
        "il_ADI": null,
        "secim_DETAY_ID": 0
    },
    {
        "muhtarlik_ID": 104789,
        "min_SANDIK_NO": "1259",
        "max_SANDIK_NO": "1259",
        "muhtarlik_ADI": "ÇINARCIK KÖYÜ",
        "cezaevi_ID": 0,
        "id": "368_0_1736",
        "birim_ID": 1736,
        "ilce_ID": 368,
        "ilce_ADI": null,
        "belde_ID": 0,
        "secim_CEVRESI_ID": 0,
        "yerlesim_YERI_TURU": 0,
        "secilecek_ADAY_SAYISI": 0,
        "il_ID": 47,
        "il_ADI": null,
        "secim_DETAY_ID": 0
    },
    {
        "muhtarlik_ID": 104790,
        "min_SANDIK_NO": "1260",
        "max_SANDIK_NO": "1261",
        "muhtarlik_ADI": "ÇIPLAK KÖYÜ",
        "cezaevi_ID": 0,
        "id": "368_0_1736",
        "birim_ID": 1736,
        "ilce_ID": 368,
        "ilce_ADI": null,
        "belde_ID": 0,
        "secim_CEVRESI_ID": 0,
        "yerlesim_YERI_TURU": 0,
        "secilecek_ADAY_SAYISI": 0,
        "il_ID": 47,
        "il_ADI": null,
        "secim_DETAY_ID": 0
    },
    {
        "muhtarlik_ID": 118620,
        "min_SANDIK_NO": "1262",
        "max_SANDIK_NO": "1262",
        "muhtarlik_ADI": "ÇİMENLİ KÖYÜ",
        "cezaevi_ID": 0,
        "id": "368_0_1736",
        "birim_ID": 1736,
        "ilce_ID": 368,
        "ilce_ADI": null,
        "belde_ID": 0,
        "secim_CEVRESI_ID": 0,
        "yerlesim_YERI_TURU": 0,
        "secilecek_ADAY_SAYISI": 0,
        "il_ID": 47,
        "il_ADI": null,
        "secim_DETAY_ID": 0
    },
    {
        "muhtarlik_ID": 104791,
        "min_SANDIK_NO": "1263",
        "max_SANDIK_NO": "1263",
        "muhtarlik_ADI": "ÇİTLİBAĞ KÖYÜ",
        "cezaevi_ID": 0,
        "id": "368_0_1736",
        "birim_ID": 1736,
        "ilce_ID": 368,
        "ilce_ADI": null,
        "belde_ID": 0,
        "secim_CEVRESI_ID": 0,
        "yerlesim_YERI_TURU": 0,
        "secilecek_ADAY_SAYISI": 0,
        "il_ID": 47,
        "il_ADI": null,
        "secim_DETAY_ID": 0
    },
    {
        "muhtarlik_ID": 104792,
        "min_SANDIK_NO": "1264",
        "max_SANDIK_NO": "1264",
        "muhtarlik_ADI": "DAMLALI KÖYÜ",
        "cezaevi_ID": 0,
        "id": "368_0_1736",
        "birim_ID": 1736,
        "ilce_ID": 368,
        "ilce_ADI": null,
        "belde_ID": 0,
        "secim_CEVRESI_ID": 0,
        "yerlesim_YERI_TURU": 0,
        "secilecek_ADAY_SAYISI": 0,
        "il_ID": 47,
        "il_ADI": null,
        "secim_DETAY_ID": 0
    },
    {
        "muhtarlik_ID": 104793,
        "min_SANDIK_NO": "1265",
        "max_SANDIK_NO": "1265",
        "muhtarlik_ADI": "DEMET KÖYÜ",
        "cezaevi_ID": 0,
        "id": "368_0_1736",
        "birim_ID": 1736,
        "ilce_ID": 368,
        "ilce_ADI": null,
        "belde_ID": 0,
        "secim_CEVRESI_ID": 0,
        "yerlesim_YERI_TURU": 0,
        "secilecek_ADAY_SAYISI": 0,
        "il_ID": 47,
        "il_ADI": null,
        "secim_DETAY_ID": 0
    },
    {
        "muhtarlik_ID": 104794,
        "min_SANDIK_NO": "1266",
        "max_SANDIK_NO": "1266",
        "muhtarlik_ADI": "DEMİRCİ KÖYÜ",
        "cezaevi_ID": 0,
        "id": "368_0_1736",
        "birim_ID": 1736,
        "ilce_ID": 368,
        "ilce_ADI": null,
        "belde_ID": 0,
        "secim_CEVRESI_ID": 0,
        "yerlesim_YERI_TURU": 0,
        "secilecek_ADAY_SAYISI": 0,
        "il_ID": 47,
        "il_ADI": null,
        "secim_DETAY_ID": 0
    },
    {
        "muhtarlik_ID": 104795,
        "min_SANDIK_NO": "1267",
        "max_SANDIK_NO": "1267",
        "muhtarlik_ADI": "DEMİRKAPI KÖYÜ",
        "cezaevi_ID": 0,
        "id": "368_0_1736",
        "birim_ID": 1736,
        "ilce_ID": 368,
        "ilce_ADI": null,
        "belde_ID": 0,
        "secim_CEVRESI_ID": 0,
        "yerlesim_YERI_TURU": 0,
        "secilecek_ADAY_SAYISI": 0,
        "il_ID": 47,
        "il_ADI": null,
        "secim_DETAY_ID": 0
    },
    {
        "muhtarlik_ID": 104883,
        "min_SANDIK_NO": "1268",
        "max_SANDIK_NO": "1268",
        "muhtarlik_ADI": "DEMİRLER KÖYÜ",
        "cezaevi_ID": 0,
        "id": "368_0_1736",
        "birim_ID": 1736,
        "ilce_ID": 368,
        "ilce_ADI": null,
        "belde_ID": 0,
        "secim_CEVRESI_ID": 0,
        "yerlesim_YERI_TURU": 0,
        "secilecek_ADAY_SAYISI": 0,
        "il_ID": 47,
        "il_ADI": null,
        "secim_DETAY_ID": 0
    },
    {
        "muhtarlik_ID": 104796,
        "min_SANDIK_NO": "1183",
        "max_SANDIK_NO": "1184",
        "muhtarlik_ADI": "DİKMEN-MİRZEOĞLU MAH.",
        "cezaevi_ID": 0,
        "id": "368_0_1736",
        "birim_ID": 1736,
        "ilce_ID": 368,
        "ilce_ADI": null,
        "belde_ID": 0,
        "secim_CEVRESI_ID": 0,
        "yerlesim_YERI_TURU": 0,
        "secilecek_ADAY_SAYISI": 0,
        "il_ID": 47,
        "il_ADI": null,
        "secim_DETAY_ID": 0
    },
    {
        "muhtarlik_ID": 104797,
        "min_SANDIK_NO": "1185",
        "max_SANDIK_NO": "1186",
        "muhtarlik_ADI": "DİKMEN-TEPEBAŞI MAH.",
        "cezaevi_ID": 0,
        "id": "368_0_1736",
        "birim_ID": 1736,
        "ilce_ID": 368,
        "ilce_ADI": null,
        "belde_ID": 0,
        "secim_CEVRESI_ID": 0,
        "yerlesim_YERI_TURU": 0,
        "secilecek_ADAY_SAYISI": 0,
        "il_ID": 47,
        "il_ADI": null,
        "secim_DETAY_ID": 0
    },
    {
        "muhtarlik_ID": 104798,
        "min_SANDIK_NO": "1187",
        "max_SANDIK_NO": "1188",
        "muhtarlik_ADI": "DİKMEN-TURGUT ÖZAL MAH.",
        "cezaevi_ID": 0,
        "id": "368_0_1736",
        "birim_ID": 1736,
        "ilce_ID": 368,
        "ilce_ADI": null,
        "belde_ID": 0,
        "secim_CEVRESI_ID": 0,
        "yerlesim_YERI_TURU": 0,
        "secilecek_ADAY_SAYISI": 0,
        "il_ID": 47,
        "il_ADI": null,
        "secim_DETAY_ID": 0
    },
    {
        "muhtarlik_ID": 104799,
        "min_SANDIK_NO": "1269",
        "max_SANDIK_NO": "1269",
        "muhtarlik_ADI": "DOĞANLI KÖYÜ",
        "cezaevi_ID": 0,
        "id": "368_0_1736",
        "birim_ID": 1736,
        "ilce_ID": 368,
        "ilce_ADI": null,
        "belde_ID": 0,
        "secim_CEVRESI_ID": 0,
        "yerlesim_YERI_TURU": 0,
        "secilecek_ADAY_SAYISI": 0,
        "il_ID": 47,
        "il_ADI": null,
        "secim_DETAY_ID": 0
    },
    {
        "muhtarlik_ID": 104801,
        "min_SANDIK_NO": "1270",
        "max_SANDIK_NO": "1270",
        "muhtarlik_ADI": "DORA KÖYÜ",
        "cezaevi_ID": 0,
        "id": "368_0_1736",
        "birim_ID": 1736,
        "ilce_ID": 368,
        "ilce_ADI": null,
        "belde_ID": 0,
        "secim_CEVRESI_ID": 0,
        "yerlesim_YERI_TURU": 0,
        "secilecek_ADAY_SAYISI": 0,
        "il_ID": 47,
        "il_ADI": null,
        "secim_DETAY_ID": 0
    },
    {
        "muhtarlik_ID": 124771,
        "min_SANDIK_NO": "1271",
        "max_SANDIK_NO": "1271",
        "muhtarlik_ADI": "DOYURAN KÖYÜ",
        "cezaevi_ID": 0,
        "id": "368_0_1736",
        "birim_ID": 1736,
        "ilce_ID": 368,
        "ilce_ADI": null,
        "belde_ID": 0,
        "secim_CEVRESI_ID": 0,
        "yerlesim_YERI_TURU": 0,
        "secilecek_ADAY_SAYISI": 0,
        "il_ID": 47,
        "il_ADI": null,
        "secim_DETAY_ID": 0
    },
    {
        "muhtarlik_ID": 104800,
        "min_SANDIK_NO": "1272",
        "max_SANDIK_NO": "1272",
        "muhtarlik_ADI": "DÖRTYOL KÖYÜ",
        "cezaevi_ID": 0,
        "id": "368_0_1736",
        "birim_ID": 1736,
        "ilce_ID": 368,
        "ilce_ADI": null,
        "belde_ID": 0,
        "secim_CEVRESI_ID": 0,
        "yerlesim_YERI_TURU": 0,
        "secilecek_ADAY_SAYISI": 0,
        "il_ID": 47,
        "il_ADI": null,
        "secim_DETAY_ID": 0
    },
    {
        "muhtarlik_ID": 118886,
        "min_SANDIK_NO": "1273",
        "max_SANDIK_NO": "1273",
        "muhtarlik_ADI": "DÜĞÜRK KÖYÜ",
        "cezaevi_ID": 0,
        "id": "368_0_1736",
        "birim_ID": 1736,
        "ilce_ID": 368,
        "ilce_ADI": null,
        "belde_ID": 0,
        "secim_CEVRESI_ID": 0,
        "yerlesim_YERI_TURU": 0,
        "secilecek_ADAY_SAYISI": 0,
        "il_ID": 47,
        "il_ADI": null,
        "secim_DETAY_ID": 0
    },
    {
        "muhtarlik_ID": 104802,
        "min_SANDIK_NO": "1274",
        "max_SANDIK_NO": "1274",
        "muhtarlik_ADI": "EKİNLİK KÖYÜ",
        "cezaevi_ID": 0,
        "id": "368_0_1736",
        "birim_ID": 1736,
        "ilce_ID": 368,
        "ilce_ADI": null,
        "belde_ID": 0,
        "secim_CEVRESI_ID": 0,
        "yerlesim_YERI_TURU": 0,
        "secilecek_ADAY_SAYISI": 0,
        "il_ID": 47,
        "il_ADI": null,
        "secim_DETAY_ID": 0
    },
    {
        "muhtarlik_ID": 104803,
        "min_SANDIK_NO": "1275",
        "max_SANDIK_NO": "1275",
        "muhtarlik_ADI": "ELBEYLİ KÖYÜ",
        "cezaevi_ID": 0,
        "id": "368_0_1736",
        "birim_ID": 1736,
        "ilce_ID": 368,
        "ilce_ADI": null,
        "belde_ID": 0,
        "secim_CEVRESI_ID": 0,
        "yerlesim_YERI_TURU": 0,
        "secilecek_ADAY_SAYISI": 0,
        "il_ID": 47,
        "il_ADI": null,
        "secim_DETAY_ID": 0
    },
    {
        "muhtarlik_ID": 124772,
        "min_SANDIK_NO": "1276",
        "max_SANDIK_NO": "1276",
        "muhtarlik_ADI": "ELMALI KÖYÜ",
        "cezaevi_ID": 0,
        "id": "368_0_1736",
        "birim_ID": 1736,
        "ilce_ID": 368,
        "ilce_ADI": null,
        "belde_ID": 0,
        "secim_CEVRESI_ID": 0,
        "yerlesim_YERI_TURU": 0,
        "secilecek_ADAY_SAYISI": 0,
        "il_ID": 47,
        "il_ADI": null,
        "secim_DETAY_ID": 0
    },
    {
        "muhtarlik_ID": 104804,
        "min_SANDIK_NO": "1277",
        "max_SANDIK_NO": "1277",
        "muhtarlik_ADI": "ERDEM KÖYÜ",
        "cezaevi_ID": 0,
        "id": "368_0_1736",
        "birim_ID": 1736,
        "ilce_ID": 368,
        "ilce_ADI": null,
        "belde_ID": 0,
        "secim_CEVRESI_ID": 0,
        "yerlesim_YERI_TURU": 0,
        "secilecek_ADAY_SAYISI": 0,
        "il_ID": 47,
        "il_ADI": null,
        "secim_DETAY_ID": 0
    },
    {
        "muhtarlik_ID": 104805,
        "min_SANDIK_NO": "1278",
        "max_SANDIK_NO": "1278",
        "muhtarlik_ADI": "ERİKLİ KÖYÜ",
        "cezaevi_ID": 0,
        "id": "368_0_1736",
        "birim_ID": 1736,
        "ilce_ID": 368,
        "ilce_ADI": null,
        "belde_ID": 0,
        "secim_CEVRESI_ID": 0,
        "yerlesim_YERI_TURU": 0,
        "secilecek_ADAY_SAYISI": 0,
        "il_ID": 47,
        "il_ADI": null,
        "secim_DETAY_ID": 0
    },
    {
        "muhtarlik_ID": 104806,
        "min_SANDIK_NO": "1279",
        "max_SANDIK_NO": "1279",
        "muhtarlik_ADI": "EROĞLU KÖYÜ",
        "cezaevi_ID": 0,
        "id": "368_0_1736",
        "birim_ID": 1736,
        "ilce_ID": 368,
        "ilce_ADI": null,
        "belde_ID": 0,
        "secim_CEVRESI_ID": 0,
        "yerlesim_YERI_TURU": 0,
        "secilecek_ADAY_SAYISI": 0,
        "il_ID": 47,
        "il_ADI": null,
        "secim_DETAY_ID": 0
    },
    {
        "muhtarlik_ID": 104749,
        "min_SANDIK_NO": "1044",
        "max_SANDIK_NO": "1056",
        "muhtarlik_ADI": "ERSOYLU MAH.",
        "cezaevi_ID": 0,
        "id": "368_0_1736",
        "birim_ID": 1736,
        "ilce_ID": 368,
        "ilce_ADI": null,
        "belde_ID": 0,
        "secim_CEVRESI_ID": 0,
        "yerlesim_YERI_TURU": 0,
        "secilecek_ADAY_SAYISI": 0,
        "il_ID": 47,
        "il_ADI": null,
        "secim_DETAY_ID": 0
    },
    {
        "muhtarlik_ID": 104807,
        "min_SANDIK_NO": "1280",
        "max_SANDIK_NO": "1280",
        "muhtarlik_ADI": "ESENLİ KÖYÜ",
        "cezaevi_ID": 0,
        "id": "368_0_1736",
        "birim_ID": 1736,
        "ilce_ID": 368,
        "ilce_ADI": null,
        "belde_ID": 0,
        "secim_CEVRESI_ID": 0,
        "yerlesim_YERI_TURU": 0,
        "secilecek_ADAY_SAYISI": 0,
        "il_ID": 47,
        "il_ADI": null,
        "secim_DETAY_ID": 0
    },
    {
        "muhtarlik_ID": 104808,
        "min_SANDIK_NO": "1281",
        "max_SANDIK_NO": "1282",
        "muhtarlik_ADI": "ESKİN KÖYÜ",
        "cezaevi_ID": 0,
        "id": "368_0_1736",
        "birim_ID": 1736,
        "ilce_ID": 368,
        "ilce_ADI": null,
        "belde_ID": 0,
        "secim_CEVRESI_ID": 0,
        "yerlesim_YERI_TURU": 0,
        "secilecek_ADAY_SAYISI": 0,
        "il_ID": 47,
        "il_ADI": null,
        "secim_DETAY_ID": 0
    },
    {
        "muhtarlik_ID": 104809,
        "min_SANDIK_NO": "1283",
        "max_SANDIK_NO": "1285",
        "muhtarlik_ADI": "EŞME KÖYÜ",
        "cezaevi_ID": 0,
        "id": "368_0_1736",
        "birim_ID": 1736,
        "ilce_ID": 368,
        "ilce_ADI": null,
        "belde_ID": 0,
        "secim_CEVRESI_ID": 0,
        "yerlesim_YERI_TURU": 0,
        "secilecek_ADAY_SAYISI": 0,
        "il_ID": 47,
        "il_ADI": null,
        "secim_DETAY_ID": 0
    },
    {
        "muhtarlik_ID": 104810,
        "min_SANDIK_NO": "1286",
        "max_SANDIK_NO": "1287",
        "muhtarlik_ADI": "EYMİRLİ KÖYÜ",
        "cezaevi_ID": 0,
        "id": "368_0_1736",
        "birim_ID": 1736,
        "ilce_ID": 368,
        "ilce_ADI": null,
        "belde_ID": 0,
        "secim_CEVRESI_ID": 0,
        "yerlesim_YERI_TURU": 0,
        "secilecek_ADAY_SAYISI": 0,
        "il_ID": 47,
        "il_ADI": null,
        "secim_DETAY_ID": 0
    },
    {
        "muhtarlik_ID": 124773,
        "min_SANDIK_NO": "1288",
        "max_SANDIK_NO": "1288",
        "muhtarlik_ADI": "FESLİĞEN KÖYÜ",
        "cezaevi_ID": 0,
        "id": "368_0_1736",
        "birim_ID": 1736,
        "ilce_ID": 368,
        "ilce_ADI": null,
        "belde_ID": 0,
        "secim_CEVRESI_ID": 0,
        "yerlesim_YERI_TURU": 0,
        "secilecek_ADAY_SAYISI": 0,
        "il_ID": 47,
        "il_ADI": null,
        "secim_DETAY_ID": 0
    },
    {
        "muhtarlik_ID": 104811,
        "min_SANDIK_NO": "1189",
        "max_SANDIK_NO": "1191",
        "muhtarlik_ADI": "GÖKÇE-CUMHURİYET MAH.",
        "cezaevi_ID": 0,
        "id": "368_0_1736",
        "birim_ID": 1736,
        "ilce_ID": 368,
        "ilce_ADI": null,
        "belde_ID": 0,
        "secim_CEVRESI_ID": 0,
        "yerlesim_YERI_TURU": 0,
        "secilecek_ADAY_SAYISI": 0,
        "il_ID": 47,
        "il_ADI": null,
        "secim_DETAY_ID": 0
    },
    {
        "muhtarlik_ID": 104812,
        "min_SANDIK_NO": "1192",
        "max_SANDIK_NO": "1193",
        "muhtarlik_ADI": "GÖKÇE-TEPEBAŞI MAH.",
        "cezaevi_ID": 0,
        "id": "368_0_1736",
        "birim_ID": 1736,
        "ilce_ID": 368,
        "ilce_ADI": null,
        "belde_ID": 0,
        "secim_CEVRESI_ID": 0,
        "yerlesim_YERI_TURU": 0,
        "secilecek_ADAY_SAYISI": 0,
        "il_ID": 47,
        "il_ADI": null,
        "secim_DETAY_ID": 0
    },
    {
        "muhtarlik_ID": 104813,
        "min_SANDIK_NO": "1194",
        "max_SANDIK_NO": "1196",
        "muhtarlik_ADI": "GÖKÇE-YENİ  MAH.",
        "cezaevi_ID": 0,
        "id": "368_0_1736",
        "birim_ID": 1736,
        "ilce_ID": 368,
        "ilce_ADI": null,
        "belde_ID": 0,
        "secim_CEVRESI_ID": 0,
        "yerlesim_YERI_TURU": 0,
        "secilecek_ADAY_SAYISI": 0,
        "il_ID": 47,
        "il_ADI": null,
        "secim_DETAY_ID": 0
    },
    {
        "muhtarlik_ID": 104814,
        "min_SANDIK_NO": "1289",
        "max_SANDIK_NO": "1289",
        "muhtarlik_ADI": "GÖLLÜ KÖYÜ",
        "cezaevi_ID": 0,
        "id": "368_0_1736",
        "birim_ID": 1736,
        "ilce_ID": 368,
        "ilce_ADI": null,
        "belde_ID": 0,
        "secim_CEVRESI_ID": 0,
        "yerlesim_YERI_TURU": 0,
        "secilecek_ADAY_SAYISI": 0,
        "il_ID": 47,
        "il_ADI": null,
        "secim_DETAY_ID": 0
    },
    {
        "muhtarlik_ID": 124775,
        "min_SANDIK_NO": "1290",
        "max_SANDIK_NO": "1290",
        "muhtarlik_ADI": "GÖZLÜCE KÖYÜ",
        "cezaevi_ID": 0,
        "id": "368_0_1736",
        "birim_ID": 1736,
        "ilce_ID": 368,
        "ilce_ADI": null,
        "belde_ID": 0,
        "secim_CEVRESI_ID": 0,
        "yerlesim_YERI_TURU": 0,
        "secilecek_ADAY_SAYISI": 0,
        "il_ID": 47,
        "il_ADI": null,
        "secim_DETAY_ID": 0
    },
    {
        "muhtarlik_ID": 124774,
        "min_SANDIK_NO": "1291",
        "max_SANDIK_NO": "1291",
        "muhtarlik_ADI": "GÜMÜŞDERE KÖYÜ",
        "cezaevi_ID": 0,
        "id": "368_0_1736",
        "birim_ID": 1736,
        "ilce_ID": 368,
        "ilce_ADI": null,
        "belde_ID": 0,
        "secim_CEVRESI_ID": 0,
        "yerlesim_YERI_TURU": 0,
        "secilecek_ADAY_SAYISI": 0,
        "il_ID": 47,
        "il_ADI": null,
        "secim_DETAY_ID": 0
    },
    {
        "muhtarlik_ID": 104879,
        "min_SANDIK_NO": "1292",
        "max_SANDIK_NO": "1292",
        "muhtarlik_ADI": "GÜNEŞTEPE KÖYÜ",
        "cezaevi_ID": 0,
        "id": "368_0_1736",
        "birim_ID": 1736,
        "ilce_ID": 368,
        "ilce_ADI": null,
        "belde_ID": 0,
        "secim_CEVRESI_ID": 0,
        "yerlesim_YERI_TURU": 0,
        "secilecek_ADAY_SAYISI": 0,
        "il_ID": 47,
        "il_ADI": null,
        "secim_DETAY_ID": 0
    },
    {
        "muhtarlik_ID": 104815,
        "min_SANDIK_NO": "1293",
        "max_SANDIK_NO": "1293",
        "muhtarlik_ADI": "GÜNGÖREN KÖYÜ",
        "cezaevi_ID": 0,
        "id": "368_0_1736",
        "birim_ID": 1736,
        "ilce_ID": 368,
        "ilce_ADI": null,
        "belde_ID": 0,
        "secim_CEVRESI_ID": 0,
        "yerlesim_YERI_TURU": 0,
        "secilecek_ADAY_SAYISI": 0,
        "il_ID": 47,
        "il_ADI": null,
        "secim_DETAY_ID": 0
    },
    {
        "muhtarlik_ID": 104816,
        "min_SANDIK_NO": "1294",
        "max_SANDIK_NO": "1295",
        "muhtarlik_ADI": "GÜNLÜCE KÖYÜ",
        "cezaevi_ID": 0,
        "id": "368_0_1736",
        "birim_ID": 1736,
        "ilce_ID": 368,
        "ilce_ADI": null,
        "belde_ID": 0,
        "secim_CEVRESI_ID": 0,
        "yerlesim_YERI_TURU": 0,
        "secilecek_ADAY_SAYISI": 0,
        "il_ID": 47,
        "il_ADI": null,
        "secim_DETAY_ID": 0
    },
    {
        "muhtarlik_ID": 104817,
        "min_SANDIK_NO": "1296",
        "max_SANDIK_NO": "1296",
        "muhtarlik_ADI": "GÜRMEŞE KÖYÜ",
        "cezaevi_ID": 0,
        "id": "368_0_1736",
        "birim_ID": 1736,
        "ilce_ID": 368,
        "ilce_ADI": null,
        "belde_ID": 0,
        "secim_CEVRESI_ID": 0,
        "yerlesim_YERI_TURU": 0,
        "secilecek_ADAY_SAYISI": 0,
        "il_ID": 47,
        "il_ADI": null,
        "secim_DETAY_ID": 0
    },
    {
        "muhtarlik_ID": 104818,
        "min_SANDIK_NO": "1297",
        "max_SANDIK_NO": "1297",
        "muhtarlik_ADI": "HACIHASAN KÖYÜ",
        "cezaevi_ID": 0,
        "id": "368_0_1736",
        "birim_ID": 1736,
        "ilce_ID": 368,
        "ilce_ADI": null,
        "belde_ID": 0,
        "secim_CEVRESI_ID": 0,
        "yerlesim_YERI_TURU": 0,
        "secilecek_ADAY_SAYISI": 0,
        "il_ID": 47,
        "il_ADI": null,
        "secim_DETAY_ID": 0
    },
    {
        "muhtarlik_ID": 104819,
        "min_SANDIK_NO": "1298",
        "max_SANDIK_NO": "1298",
        "muhtarlik_ADI": "HACIYUSUF KÖYÜ",
        "cezaevi_ID": 0,
        "id": "368_0_1736",
        "birim_ID": 1736,
        "ilce_ID": 368,
        "ilce_ADI": null,
        "belde_ID": 0,
        "secim_CEVRESI_ID": 0,
        "yerlesim_YERI_TURU": 0,
        "secilecek_ADAY_SAYISI": 0,
        "il_ID": 47,
        "il_ADI": null,
        "secim_DETAY_ID": 0
    },
    {
        "muhtarlik_ID": 104820,
        "min_SANDIK_NO": "1299",
        "max_SANDIK_NO": "1299",
        "muhtarlik_ADI": "HAKVERDİ KÖYÜ",
        "cezaevi_ID": 0,
        "id": "368_0_1736",
        "birim_ID": 1736,
        "ilce_ID": 368,
        "ilce_ADI": null,
        "belde_ID": 0,
        "secim_CEVRESI_ID": 0,
        "yerlesim_YERI_TURU": 0,
        "secilecek_ADAY_SAYISI": 0,
        "il_ID": 47,
        "il_ADI": null,
        "secim_DETAY_ID": 0
    },
    {
        "muhtarlik_ID": 104821,
        "min_SANDIK_NO": "1300",
        "max_SANDIK_NO": "1300",
        "muhtarlik_ADI": "HALKALI KÖYÜ",
        "cezaevi_ID": 0,
        "id": "368_0_1736",
        "birim_ID": 1736,
        "ilce_ID": 368,
        "ilce_ADI": null,
        "belde_ID": 0,
        "secim_CEVRESI_ID": 0,
        "yerlesim_YERI_TURU": 0,
        "secilecek_ADAY_SAYISI": 0,
        "il_ID": 47,
        "il_ADI": null,
        "secim_DETAY_ID": 0
    },
    {
        "muhtarlik_ID": 104822,
        "min_SANDIK_NO": "1301",
        "max_SANDIK_NO": "1301",
        "muhtarlik_ADI": "HARMANDÜZÜ KÖYÜ",
        "cezaevi_ID": 0,
        "id": "368_0_1736",
        "birim_ID": 1736,
        "ilce_ID": 368,
        "ilce_ADI": null,
        "belde_ID": 0,
        "secim_CEVRESI_ID": 0,
        "yerlesim_YERI_TURU": 0,
        "secilecek_ADAY_SAYISI": 0,
        "il_ID": 47,
        "il_ADI": null,
        "secim_DETAY_ID": 0
    },
    {
        "muhtarlik_ID": 124776,
        "min_SANDIK_NO": "1302",
        "max_SANDIK_NO": "1302",
        "muhtarlik_ADI": "HAZNEDAR KÖYÜ",
        "cezaevi_ID": 0,
        "id": "368_0_1736",
        "birim_ID": 1736,
        "ilce_ID": 368,
        "ilce_ADI": null,
        "belde_ID": 0,
        "secim_CEVRESI_ID": 0,
        "yerlesim_YERI_TURU": 0,
        "secilecek_ADAY_SAYISI": 0,
        "il_ID": 47,
        "il_ADI": null,
        "secim_DETAY_ID": 0
    },
    {
        "muhtarlik_ID": 104823,
        "min_SANDIK_NO": "1303",
        "max_SANDIK_NO": "1305",
        "muhtarlik_ADI": "HOCAKÖY",
        "cezaevi_ID": 0,
        "id": "368_0_1736",
        "birim_ID": 1736,
        "ilce_ID": 368,
        "ilce_ADI": null,
        "belde_ID": 0,
        "secim_CEVRESI_ID": 0,
        "yerlesim_YERI_TURU": 0,
        "secilecek_ADAY_SAYISI": 0,
        "il_ID": 47,
        "il_ADI": null,
        "secim_DETAY_ID": 0
    },
    {
        "muhtarlik_ID": 104824,
        "min_SANDIK_NO": "1306",
        "max_SANDIK_NO": "1306",
        "muhtarlik_ADI": "ILICAK KÖYÜ",
        "cezaevi_ID": 0,
        "id": "368_0_1736",
        "birim_ID": 1736,
        "ilce_ID": 368,
        "ilce_ADI": null,
        "belde_ID": 0,
        "secim_CEVRESI_ID": 0,
        "yerlesim_YERI_TURU": 0,
        "secilecek_ADAY_SAYISI": 0,
        "il_ID": 47,
        "il_ADI": null,
        "secim_DETAY_ID": 0
    },
    {
        "muhtarlik_ID": 104825,
        "min_SANDIK_NO": "1307",
        "max_SANDIK_NO": "1308",
        "muhtarlik_ADI": "IŞIKLAR KÖYÜ",
        "cezaevi_ID": 0,
        "id": "368_0_1736",
        "birim_ID": 1736,
        "ilce_ID": 368,
        "ilce_ADI": null,
        "belde_ID": 0,
        "secim_CEVRESI_ID": 0,
        "yerlesim_YERI_TURU": 0,
        "secilecek_ADAY_SAYISI": 0,
        "il_ID": 47,
        "il_ADI": null,
        "secim_DETAY_ID": 0
    },
    {
        "muhtarlik_ID": 124777,
        "min_SANDIK_NO": "1309",
        "max_SANDIK_NO": "1309",
        "muhtarlik_ADI": "IŞIKÖREN KÖYÜ",
        "cezaevi_ID": 0,
        "id": "368_0_1736",
        "birim_ID": 1736,
        "ilce_ID": 368,
        "ilce_ADI": null,
        "belde_ID": 0,
        "secim_CEVRESI_ID": 0,
        "yerlesim_YERI_TURU": 0,
        "secilecek_ADAY_SAYISI": 0,
        "il_ID": 47,
        "il_ADI": null,
        "secim_DETAY_ID": 0
    },
    {
        "muhtarlik_ID": 104826,
        "min_SANDIK_NO": "1310",
        "max_SANDIK_NO": "1310",
        "muhtarlik_ADI": "İKİKUYU KÖYÜ",
        "cezaevi_ID": 0,
        "id": "368_0_1736",
        "birim_ID": 1736,
        "ilce_ID": 368,
        "ilce_ADI": null,
        "belde_ID": 0,
        "secim_CEVRESI_ID": 0,
        "yerlesim_YERI_TURU": 0,
        "secilecek_ADAY_SAYISI": 0,
        "il_ID": 47,
        "il_ADI": null,
        "secim_DETAY_ID": 0
    },
    {
        "muhtarlik_ID": 104884,
        "min_SANDIK_NO": "1311",
        "max_SANDIK_NO": "1311",
        "muhtarlik_ADI": "İKİZLER KÖYÜ",
        "cezaevi_ID": 0,
        "id": "368_0_1736",
        "birim_ID": 1736,
        "ilce_ID": 368,
        "ilce_ADI": null,
        "belde_ID": 0,
        "secim_CEVRESI_ID": 0,
        "yerlesim_YERI_TURU": 0,
        "secilecek_ADAY_SAYISI": 0,
        "il_ID": 47,
        "il_ADI": null,
        "secim_DETAY_ID": 0
    },
    {
        "muhtarlik_ID": 104827,
        "min_SANDIK_NO": "1312",
        "max_SANDIK_NO": "1312",
        "muhtarlik_ADI": "İNANDI KÖYÜ",
        "cezaevi_ID": 0,
        "id": "368_0_1736",
        "birim_ID": 1736,
        "ilce_ID": 368,
        "ilce_ADI": null,
        "belde_ID": 0,
        "secim_CEVRESI_ID": 0,
        "yerlesim_YERI_TURU": 0,
        "secilecek_ADAY_SAYISI": 0,
        "il_ID": 47,
        "il_ADI": null,
        "secim_DETAY_ID": 0
    },
    {
        "muhtarlik_ID": 104755,
        "min_SANDIK_NO": "1057",
        "max_SANDIK_NO": "1087",
        "muhtarlik_ADI": "İPEK MAH.",
        "cezaevi_ID": 0,
        "id": "368_0_1736",
        "birim_ID": 1736,
        "ilce_ID": 368,
        "ilce_ADI": null,
        "belde_ID": 0,
        "secim_CEVRESI_ID": 0,
        "yerlesim_YERI_TURU": 0,
        "secilecek_ADAY_SAYISI": 0,
        "il_ID": 47,
        "il_ADI": null,
        "secim_DETAY_ID": 0
    },
    {
        "muhtarlik_ID": 104828,
        "min_SANDIK_NO": "1313",
        "max_SANDIK_NO": "1313",
        "muhtarlik_ADI": "KALAYCIK KÖYÜ",
        "cezaevi_ID": 0,
        "id": "368_0_1736",
        "birim_ID": 1736,
        "ilce_ID": 368,
        "ilce_ADI": null,
        "belde_ID": 0,
        "secim_CEVRESI_ID": 0,
        "yerlesim_YERI_TURU": 0,
        "secilecek_ADAY_SAYISI": 0,
        "il_ID": 47,
        "il_ADI": null,
        "secim_DETAY_ID": 0
    },
    {
        "muhtarlik_ID": 104829,
        "min_SANDIK_NO": "1314",
        "max_SANDIK_NO": "1314",
        "muhtarlik_ADI": "KARABENT KÖYÜ",
        "cezaevi_ID": 0,
        "id": "368_0_1736",
        "birim_ID": 1736,
        "ilce_ID": 368,
        "ilce_ADI": null,
        "belde_ID": 0,
        "secim_CEVRESI_ID": 0,
        "yerlesim_YERI_TURU": 0,
        "secilecek_ADAY_SAYISI": 0,
        "il_ID": 47,
        "il_ADI": null,
        "secim_DETAY_ID": 0
    },
    {
        "muhtarlik_ID": 104830,
        "min_SANDIK_NO": "1315",
        "max_SANDIK_NO": "1315",
        "muhtarlik_ADI": "KARAKULAK KÖYÜ",
        "cezaevi_ID": 0,
        "id": "368_0_1736",
        "birim_ID": 1736,
        "ilce_ID": 368,
        "ilce_ADI": null,
        "belde_ID": 0,
        "secim_CEVRESI_ID": 0,
        "yerlesim_YERI_TURU": 0,
        "secilecek_ADAY_SAYISI": 0,
        "il_ID": 47,
        "il_ADI": null,
        "secim_DETAY_ID": 0
    },
    {
        "muhtarlik_ID": 104831,
        "min_SANDIK_NO": "1316",
        "max_SANDIK_NO": "1317",
        "muhtarlik_ADI": "KARAKUYU KÖYÜ",
        "cezaevi_ID": 0,
        "id": "368_0_1736",
        "birim_ID": 1736,
        "ilce_ID": 368,
        "ilce_ADI": null,
        "belde_ID": 0,
        "secim_CEVRESI_ID": 0,
        "yerlesim_YERI_TURU": 0,
        "secilecek_ADAY_SAYISI": 0,
        "il_ID": 47,
        "il_ADI": null,
        "secim_DETAY_ID": 0
    },
    {
        "muhtarlik_ID": 104832,
        "min_SANDIK_NO": "1318",
        "max_SANDIK_NO": "1318",
        "muhtarlik_ADI": "KARAMAN KÖYÜ",
        "cezaevi_ID": 0,
        "id": "368_0_1736",
        "birim_ID": 1736,
        "ilce_ID": 368,
        "ilce_ADI": null,
        "belde_ID": 0,
        "secim_CEVRESI_ID": 0,
        "yerlesim_YERI_TURU": 0,
        "secilecek_ADAY_SAYISI": 0,
        "il_ID": 47,
        "il_ADI": null,
        "secim_DETAY_ID": 0
    },
    {
        "muhtarlik_ID": 104833,
        "min_SANDIK_NO": "1319",
        "max_SANDIK_NO": "1319",
        "muhtarlik_ADI": "KAŞIKLI KÖYÜ",
        "cezaevi_ID": 0,
        "id": "368_0_1736",
        "birim_ID": 1736,
        "ilce_ID": 368,
        "ilce_ADI": null,
        "belde_ID": 0,
        "secim_CEVRESI_ID": 0,
        "yerlesim_YERI_TURU": 0,
        "secilecek_ADAY_SAYISI": 0,
        "il_ID": 47,
        "il_ADI": null,
        "secim_DETAY_ID": 0
    },
    {
        "muhtarlik_ID": 104834,
        "min_SANDIK_NO": "1320",
        "max_SANDIK_NO": "1320",
        "muhtarlik_ADI": "KATARLI KÖYÜ",
        "cezaevi_ID": 0,
        "id": "368_0_1736",
        "birim_ID": 1736,
        "ilce_ID": 368,
        "ilce_ADI": null,
        "belde_ID": 0,
        "secim_CEVRESI_ID": 0,
        "yerlesim_YERI_TURU": 0,
        "secilecek_ADAY_SAYISI": 0,
        "il_ID": 47,
        "il_ADI": null,
        "secim_DETAY_ID": 0
    },
    {
        "muhtarlik_ID": 104836,
        "min_SANDIK_NO": "1321",
        "max_SANDIK_NO": "1321",
        "muhtarlik_ADI": "KAYNARCA KÖYÜ",
        "cezaevi_ID": 0,
        "id": "368_0_1736",
        "birim_ID": 1736,
        "ilce_ID": 368,
        "ilce_ADI": null,
        "belde_ID": 0,
        "secim_CEVRESI_ID": 0,
        "yerlesim_YERI_TURU": 0,
        "secilecek_ADAY_SAYISI": 0,
        "il_ID": 47,
        "il_ADI": null,
        "secim_DETAY_ID": 0
    },
    {
        "muhtarlik_ID": 124778,
        "min_SANDIK_NO": "1322",
        "max_SANDIK_NO": "1322",
        "muhtarlik_ADI": "KENGERLİ KÖYÜ",
        "cezaevi_ID": 0,
        "id": "368_0_1736",
        "birim_ID": 1736,
        "ilce_ID": 368,
        "ilce_ADI": null,
        "belde_ID": 0,
        "secim_CEVRESI_ID": 0,
        "yerlesim_YERI_TURU": 0,
        "secilecek_ADAY_SAYISI": 0,
        "il_ID": 47,
        "il_ADI": null,
        "secim_DETAY_ID": 0
    },
    {
        "muhtarlik_ID": 104837,
        "min_SANDIK_NO": "1323",
        "max_SANDIK_NO": "1323",
        "muhtarlik_ADI": "KILDUMAN KÖYÜ",
        "cezaevi_ID": 0,
        "id": "368_0_1736",
        "birim_ID": 1736,
        "ilce_ID": 368,
        "ilce_ADI": null,
        "belde_ID": 0,
        "secim_CEVRESI_ID": 0,
        "yerlesim_YERI_TURU": 0,
        "secilecek_ADAY_SAYISI": 0,
        "il_ID": 47,
        "il_ADI": null,
        "secim_DETAY_ID": 0
    },
    {
        "muhtarlik_ID": 104880,
        "min_SANDIK_NO": "1324",
        "max_SANDIK_NO": "1324",
        "muhtarlik_ADI": "KIRKKUYU KÖYÜ",
        "cezaevi_ID": 0,
        "id": "368_0_1736",
        "birim_ID": 1736,
        "ilce_ID": 368,
        "ilce_ADI": null,
        "belde_ID": 0,
        "secim_CEVRESI_ID": 0,
        "yerlesim_YERI_TURU": 0,
        "secilecek_ADAY_SAYISI": 0,
        "il_ID": 47,
        "il_ADI": null,
        "secim_DETAY_ID": 0
    },
    {
        "muhtarlik_ID": 104838,
        "min_SANDIK_NO": "1325",
        "max_SANDIK_NO": "1325",
        "muhtarlik_ADI": "KİLİMLİ KÖYÜ",
        "cezaevi_ID": 0,
        "id": "368_0_1736",
        "birim_ID": 1736,
        "ilce_ID": 368,
        "ilce_ADI": null,
        "belde_ID": 0,
        "secim_CEVRESI_ID": 0,
        "yerlesim_YERI_TURU": 0,
        "secilecek_ADAY_SAYISI": 0,
        "il_ID": 47,
        "il_ADI": null,
        "secim_DETAY_ID": 0
    },
    {
        "muhtarlik_ID": 104839,
        "min_SANDIK_NO": "1326",
        "max_SANDIK_NO": "1326",
        "muhtarlik_ADI": "KOCALAR KÖYÜ",
        "cezaevi_ID": 0,
        "id": "368_0_1736",
        "birim_ID": 1736,
        "ilce_ID": 368,
        "ilce_ADI": null,
        "belde_ID": 0,
        "secim_CEVRESI_ID": 0,
        "yerlesim_YERI_TURU": 0,
        "secilecek_ADAY_SAYISI": 0,
        "il_ID": 47,
        "il_ADI": null,
        "secim_DETAY_ID": 0
    },
    {
        "muhtarlik_ID": 104750,
        "min_SANDIK_NO": "1088",
        "max_SANDIK_NO": "1110",
        "muhtarlik_ADI": "KOÇHİSAR MAH.",
        "cezaevi_ID": 0,
        "id": "368_0_1736",
        "birim_ID": 1736,
        "ilce_ID": 368,
        "ilce_ADI": null,
        "belde_ID": 0,
        "secim_CEVRESI_ID": 0,
        "yerlesim_YERI_TURU": 0,
        "secilecek_ADAY_SAYISI": 0,
        "il_ID": 47,
        "il_ADI": null,
        "secim_DETAY_ID": 0
    },
    {
        "muhtarlik_ID": 104840,
        "min_SANDIK_NO": "1327",
        "max_SANDIK_NO": "1327",
        "muhtarlik_ADI": "KOÇLU KÖYÜ",
        "cezaevi_ID": 0,
        "id": "368_0_1736",
        "birim_ID": 1736,
        "ilce_ID": 368,
        "ilce_ADI": null,
        "belde_ID": 0,
        "secim_CEVRESI_ID": 0,
        "yerlesim_YERI_TURU": 0,
        "secilecek_ADAY_SAYISI": 0,
        "il_ID": 47,
        "il_ADI": null,
        "secim_DETAY_ID": 0
    },
    {
        "muhtarlik_ID": 118622,
        "min_SANDIK_NO": "1328",
        "max_SANDIK_NO": "1328",
        "muhtarlik_ADI": "KONUKLU KÖYÜ",
        "cezaevi_ID": 0,
        "id": "368_0_1736",
        "birim_ID": 1736,
        "ilce_ID": 368,
        "ilce_ADI": null,
        "belde_ID": 0,
        "secim_CEVRESI_ID": 0,
        "yerlesim_YERI_TURU": 0,
        "secilecek_ADAY_SAYISI": 0,
        "il_ID": 47,
        "il_ADI": null,
        "secim_DETAY_ID": 0
    },
    {
        "muhtarlik_ID": 104841,
        "min_SANDIK_NO": "1329",
        "max_SANDIK_NO": "1329",
        "muhtarlik_ADI": "KÖPRÜBAŞI KÖYÜ",
        "cezaevi_ID": 0,
        "id": "368_0_1736",
        "birim_ID": 1736,
        "ilce_ID": 368,
        "ilce_ADI": null,
        "belde_ID": 0,
        "secim_CEVRESI_ID": 0,
        "yerlesim_YERI_TURU": 0,
        "secilecek_ADAY_SAYISI": 0,
        "il_ID": 47,
        "il_ADI": null,
        "secim_DETAY_ID": 0
    },
    {
        "muhtarlik_ID": 104842,
        "min_SANDIK_NO": "1330",
        "max_SANDIK_NO": "1330",
        "muhtarlik_ADI": "KÖRSU KÖYÜ",
        "cezaevi_ID": 0,
        "id": "368_0_1736",
        "birim_ID": 1736,
        "ilce_ID": 368,
        "ilce_ADI": null,
        "belde_ID": 0,
        "secim_CEVRESI_ID": 0,
        "yerlesim_YERI_TURU": 0,
        "secilecek_ADAY_SAYISI": 0,
        "il_ID": 47,
        "il_ADI": null,
        "secim_DETAY_ID": 0
    },
    {
        "muhtarlik_ID": 104843,
        "min_SANDIK_NO": "1331",
        "max_SANDIK_NO": "1331",
        "muhtarlik_ADI": "KÜÇÜKAYRIK KÖYÜ",
        "cezaevi_ID": 0,
        "id": "368_0_1736",
        "birim_ID": 1736,
        "ilce_ID": 368,
        "ilce_ADI": null,
        "belde_ID": 0,
        "secim_CEVRESI_ID": 0,
        "yerlesim_YERI_TURU": 0,
        "secilecek_ADAY_SAYISI": 0,
        "il_ID": 47,
        "il_ADI": null,
        "secim_DETAY_ID": 0
    },
    {
        "muhtarlik_ID": 126381,
        "min_SANDIK_NO": "1332",
        "max_SANDIK_NO": "1332",
        "muhtarlik_ADI": "KÜÇÜKBOĞAZİYE KÖYÜ",
        "cezaevi_ID": 0,
        "id": "368_0_1736",
        "birim_ID": 1736,
        "ilce_ID": 368,
        "ilce_ADI": null,
        "belde_ID": 0,
        "secim_CEVRESI_ID": 0,
        "yerlesim_YERI_TURU": 0,
        "secilecek_ADAY_SAYISI": 0,
        "il_ID": 47,
        "il_ADI": null,
        "secim_DETAY_ID": 0
    },
    {
        "muhtarlik_ID": 104844,
        "min_SANDIK_NO": "1333",
        "max_SANDIK_NO": "1333",
        "muhtarlik_ADI": "KÜPLÜCE KÖYÜ",
        "cezaevi_ID": 0,
        "id": "368_0_1736",
        "birim_ID": 1736,
        "ilce_ID": 368,
        "ilce_ADI": null,
        "belde_ID": 0,
        "secim_CEVRESI_ID": 0,
        "yerlesim_YERI_TURU": 0,
        "secilecek_ADAY_SAYISI": 0,
        "il_ID": 47,
        "il_ADI": null,
        "secim_DETAY_ID": 0
    },
    {
        "muhtarlik_ID": 104845,
        "min_SANDIK_NO": "1334",
        "max_SANDIK_NO": "1334",
        "muhtarlik_ADI": "ODAKÖY",
        "cezaevi_ID": 0,
        "id": "368_0_1736",
        "birim_ID": 1736,
        "ilce_ID": 368,
        "ilce_ADI": null,
        "belde_ID": 0,
        "secim_CEVRESI_ID": 0,
        "yerlesim_YERI_TURU": 0,
        "secilecek_ADAY_SAYISI": 0,
        "il_ID": 47,
        "il_ADI": null,
        "secim_DETAY_ID": 0
    },
    {
        "muhtarlik_ID": 126250,
        "min_SANDIK_NO": "1335",
        "max_SANDIK_NO": "1335",
        "muhtarlik_ADI": "OFİS KÖYÜ",
        "cezaevi_ID": 0,
        "id": "368_0_1736",
        "birim_ID": 1736,
        "ilce_ID": 368,
        "ilce_ADI": null,
        "belde_ID": 0,
        "secim_CEVRESI_ID": 0,
        "yerlesim_YERI_TURU": 0,
        "secilecek_ADAY_SAYISI": 0,
        "il_ID": 47,
        "il_ADI": null,
        "secim_DETAY_ID": 0
    },
    {
        "muhtarlik_ID": 118602,
        "min_SANDIK_NO": "1336",
        "max_SANDIK_NO": "1336",
        "muhtarlik_ADI": "ORTAKÖY",
        "cezaevi_ID": 0,
        "id": "368_0_1736",
        "birim_ID": 1736,
        "ilce_ID": 368,
        "ilce_ADI": null,
        "belde_ID": 0,
        "secim_CEVRESI_ID": 0,
        "yerlesim_YERI_TURU": 0,
        "secilecek_ADAY_SAYISI": 0,
        "il_ID": 47,
        "il_ADI": null,
        "secim_DETAY_ID": 0
    },
    {
        "muhtarlik_ID": 104846,
        "min_SANDIK_NO": "1337",
        "max_SANDIK_NO": "1337",
        "muhtarlik_ADI": "OTLUK KÖYÜ",
        "cezaevi_ID": 0,
        "id": "368_0_1736",
        "birim_ID": 1736,
        "ilce_ID": 368,
        "ilce_ADI": null,
        "belde_ID": 0,
        "secim_CEVRESI_ID": 0,
        "yerlesim_YERI_TURU": 0,
        "secilecek_ADAY_SAYISI": 0,
        "il_ID": 47,
        "il_ADI": null,
        "secim_DETAY_ID": 0
    },
    {
        "muhtarlik_ID": 104847,
        "min_SANDIK_NO": "1338",
        "max_SANDIK_NO": "1338",
        "muhtarlik_ADI": "ÖRENCİK KÖYÜ",
        "cezaevi_ID": 0,
        "id": "368_0_1736",
        "birim_ID": 1736,
        "ilce_ID": 368,
        "ilce_ADI": null,
        "belde_ID": 0,
        "secim_CEVRESI_ID": 0,
        "yerlesim_YERI_TURU": 0,
        "secilecek_ADAY_SAYISI": 0,
        "il_ID": 47,
        "il_ADI": null,
        "secim_DETAY_ID": 0
    },
    {
        "muhtarlik_ID": 104751,
        "min_SANDIK_NO": "1111",
        "max_SANDIK_NO": "1115",
        "muhtarlik_ADI": "SANAYİ MAH.",
        "cezaevi_ID": 0,
        "id": "368_0_1736",
        "birim_ID": 1736,
        "ilce_ID": 368,
        "ilce_ADI": null,
        "belde_ID": 0,
        "secim_CEVRESI_ID": 0,
        "yerlesim_YERI_TURU": 0,
        "secilecek_ADAY_SAYISI": 0,
        "il_ID": 47,
        "il_ADI": null,
        "secim_DETAY_ID": 0
    },
    {
        "muhtarlik_ID": 104848,
        "min_SANDIK_NO": "1339",
        "max_SANDIK_NO": "1339",
        "muhtarlik_ADI": "SANCARLI KÖYÜ",
        "cezaevi_ID": 0,
        "id": "368_0_1736",
        "birim_ID": 1736,
        "ilce_ID": 368,
        "ilce_ADI": null,
        "belde_ID": 0,
        "secim_CEVRESI_ID": 0,
        "yerlesim_YERI_TURU": 0,
        "secilecek_ADAY_SAYISI": 0,
        "il_ID": 47,
        "il_ADI": null,
        "secim_DETAY_ID": 0
    },
    {
        "muhtarlik_ID": 104849,
        "min_SANDIK_NO": "1340",
        "max_SANDIK_NO": "1340",
        "muhtarlik_ADI": "SANDIKLI KÖYÜ",
        "cezaevi_ID": 0,
        "id": "368_0_1736",
        "birim_ID": 1736,
        "ilce_ID": 368,
        "ilce_ADI": null,
        "belde_ID": 0,
        "secim_CEVRESI_ID": 0,
        "yerlesim_YERI_TURU": 0,
        "secilecek_ADAY_SAYISI": 0,
        "il_ID": 47,
        "il_ADI": null,
        "secim_DETAY_ID": 0
    },
    {
        "muhtarlik_ID": 104850,
        "min_SANDIK_NO": "1341",
        "max_SANDIK_NO": "1341",
        "muhtarlik_ADI": "SARICA KÖYÜ",
        "cezaevi_ID": 0,
        "id": "368_0_1736",
        "birim_ID": 1736,
        "ilce_ID": 368,
        "ilce_ADI": null,
        "belde_ID": 0,
        "secim_CEVRESI_ID": 0,
        "yerlesim_YERI_TURU": 0,
        "secilecek_ADAY_SAYISI": 0,
        "il_ID": 47,
        "il_ADI": null,
        "secim_DETAY_ID": 0
    },
    {
        "muhtarlik_ID": 126269,
        "min_SANDIK_NO": "1342",
        "max_SANDIK_NO": "1342",
        "muhtarlik_ADI": "SARUHAN KÖYÜ",
        "cezaevi_ID": 0,
        "id": "368_0_1736",
        "birim_ID": 1736,
        "ilce_ID": 368,
        "ilce_ADI": null,
        "belde_ID": 0,
        "secim_CEVRESI_ID": 0,
        "yerlesim_YERI_TURU": 0,
        "secilecek_ADAY_SAYISI": 0,
        "il_ID": 47,
        "il_ADI": null,
        "secim_DETAY_ID": 0
    },
    {
        "muhtarlik_ID": 124779,
        "min_SANDIK_NO": "1343",
        "max_SANDIK_NO": "1343",
        "muhtarlik_ADI": "SEVİMLİ KÖYÜ",
        "cezaevi_ID": 0,
        "id": "368_0_1736",
        "birim_ID": 1736,
        "ilce_ID": 368,
        "ilce_ADI": null,
        "belde_ID": 0,
        "secim_CEVRESI_ID": 0,
        "yerlesim_YERI_TURU": 0,
        "secilecek_ADAY_SAYISI": 0,
        "il_ID": 47,
        "il_ADI": null,
        "secim_DETAY_ID": 0
    },
    {
        "muhtarlik_ID": 104851,
        "min_SANDIK_NO": "1344",
        "max_SANDIK_NO": "1344",
        "muhtarlik_ADI": "SOĞANLI KÖYÜ",
        "cezaevi_ID": 0,
        "id": "368_0_1736",
        "birim_ID": 1736,
        "ilce_ID": 368,
        "ilce_ADI": null,
        "belde_ID": 0,
        "secim_CEVRESI_ID": 0,
        "yerlesim_YERI_TURU": 0,
        "secilecek_ADAY_SAYISI": 0,
        "il_ID": 47,
        "il_ADI": null,
        "secim_DETAY_ID": 0
    },
    {
        "muhtarlik_ID": 104852,
        "min_SANDIK_NO": "1345",
        "max_SANDIK_NO": "1347",
        "muhtarlik_ADI": "SÜREKLİ KÖYÜ",
        "cezaevi_ID": 0,
        "id": "368_0_1736",
        "birim_ID": 1736,
        "ilce_ID": 368,
        "ilce_ADI": null,
        "belde_ID": 0,
        "secim_CEVRESI_ID": 0,
        "yerlesim_YERI_TURU": 0,
        "secilecek_ADAY_SAYISI": 0,
        "il_ID": 47,
        "il_ADI": null,
        "secim_DETAY_ID": 0
    },
    {
        "muhtarlik_ID": 124761,
        "min_SANDIK_NO": "1197",
        "max_SANDIK_NO": "1197",
        "muhtarlik_ADI": "ŞENYURT-CUMHURİYET MAH.",
        "cezaevi_ID": 0,
        "id": "368_0_1736",
        "birim_ID": 1736,
        "ilce_ID": 368,
        "ilce_ADI": null,
        "belde_ID": 0,
        "secim_CEVRESI_ID": 0,
        "yerlesim_YERI_TURU": 0,
        "secilecek_ADAY_SAYISI": 0,
        "il_ID": 47,
        "il_ADI": null,
        "secim_DETAY_ID": 0
    },
    {
        "muhtarlik_ID": 124762,
        "min_SANDIK_NO": "1198",
        "max_SANDIK_NO": "1198",
        "muhtarlik_ADI": "ŞENYURT-HANYERİ MAH.",
        "cezaevi_ID": 0,
        "id": "368_0_1736",
        "birim_ID": 1736,
        "ilce_ID": 368,
        "ilce_ADI": null,
        "belde_ID": 0,
        "secim_CEVRESI_ID": 0,
        "yerlesim_YERI_TURU": 0,
        "secilecek_ADAY_SAYISI": 0,
        "il_ID": 47,
        "il_ADI": null,
        "secim_DETAY_ID": 0
    },
    {
        "muhtarlik_ID": 124763,
        "min_SANDIK_NO": "1199",
        "max_SANDIK_NO": "1200",
        "muhtarlik_ADI": "ŞENYURT-NAİFOĞLU MAH.",
        "cezaevi_ID": 0,
        "id": "368_0_1736",
        "birim_ID": 1736,
        "ilce_ID": 368,
        "ilce_ADI": null,
        "belde_ID": 0,
        "secim_CEVRESI_ID": 0,
        "yerlesim_YERI_TURU": 0,
        "secilecek_ADAY_SAYISI": 0,
        "il_ID": 47,
        "il_ADI": null,
        "secim_DETAY_ID": 0
    },
    {
        "muhtarlik_ID": 124764,
        "min_SANDIK_NO": "1201",
        "max_SANDIK_NO": "1201",
        "muhtarlik_ADI": "ŞENYURT-SALKIM MAH.",
        "cezaevi_ID": 0,
        "id": "368_0_1736",
        "birim_ID": 1736,
        "ilce_ID": 368,
        "ilce_ADI": null,
        "belde_ID": 0,
        "secim_CEVRESI_ID": 0,
        "yerlesim_YERI_TURU": 0,
        "secilecek_ADAY_SAYISI": 0,
        "il_ID": 47,
        "il_ADI": null,
        "secim_DETAY_ID": 0
    },
    {
        "muhtarlik_ID": 124780,
        "min_SANDIK_NO": "1348",
        "max_SANDIK_NO": "1348",
        "muhtarlik_ADI": "TANRIVERDİ KÖYÜ",
        "cezaevi_ID": 0,
        "id": "368_0_1736",
        "birim_ID": 1736,
        "ilce_ID": 368,
        "ilce_ADI": null,
        "belde_ID": 0,
        "secim_CEVRESI_ID": 0,
        "yerlesim_YERI_TURU": 0,
        "secilecek_ADAY_SAYISI": 0,
        "il_ID": 47,
        "il_ADI": null,
        "secim_DETAY_ID": 0
    },
    {
        "muhtarlik_ID": 104892,
        "min_SANDIK_NO": "1349",
        "max_SANDIK_NO": "1349",
        "muhtarlik_ADI": "TARLABAŞI KÖYÜ",
        "cezaevi_ID": 0,
        "id": "368_0_1736",
        "birim_ID": 1736,
        "ilce_ID": 368,
        "ilce_ADI": null,
        "belde_ID": 0,
        "secim_CEVRESI_ID": 0,
        "yerlesim_YERI_TURU": 0,
        "secilecek_ADAY_SAYISI": 0,
        "il_ID": 47,
        "il_ADI": null,
        "secim_DETAY_ID": 0
    },
    {
        "muhtarlik_ID": 104853,
        "min_SANDIK_NO": "1350",
        "max_SANDIK_NO": "1350",
        "muhtarlik_ADI": "TAŞLICA KÖYÜ",
        "cezaevi_ID": 0,
        "id": "368_0_1736",
        "birim_ID": 1736,
        "ilce_ID": 368,
        "ilce_ADI": null,
        "belde_ID": 0,
        "secim_CEVRESI_ID": 0,
        "yerlesim_YERI_TURU": 0,
        "secilecek_ADAY_SAYISI": 0,
        "il_ID": 47,
        "il_ADI": null,
        "secim_DETAY_ID": 0
    },
    {
        "muhtarlik_ID": 104882,
        "min_SANDIK_NO": "1351",
        "max_SANDIK_NO": "1351",
        "muhtarlik_ADI": "TATLICA KÖYÜ",
        "cezaevi_ID": 0,
        "id": "368_0_1736",
        "birim_ID": 1736,
        "ilce_ID": 368,
        "ilce_ADI": null,
        "belde_ID": 0,
        "secim_CEVRESI_ID": 0,
        "yerlesim_YERI_TURU": 0,
        "secilecek_ADAY_SAYISI": 0,
        "il_ID": 47,
        "il_ADI": null,
        "secim_DETAY_ID": 0
    },
    {
        "muhtarlik_ID": 104752,
        "min_SANDIK_NO": "1116",
        "max_SANDIK_NO": "1143",
        "muhtarlik_ADI": "TEPEBAŞI MAH.",
        "cezaevi_ID": 0,
        "id": "368_0_1736",
        "birim_ID": 1736,
        "ilce_ID": 368,
        "ilce_ADI": null,
        "belde_ID": 0,
        "secim_CEVRESI_ID": 0,
        "yerlesim_YERI_TURU": 0,
        "secilecek_ADAY_SAYISI": 0,
        "il_ID": 47,
        "il_ADI": null,
        "secim_DETAY_ID": 0
    },
    {
        "muhtarlik_ID": 104835,
        "min_SANDIK_NO": "1352",
        "max_SANDIK_NO": "1352",
        "muhtarlik_ADI": "TIRAŞLI KÖYÜ",
        "cezaevi_ID": 0,
        "id": "368_0_1736",
        "birim_ID": 1736,
        "ilce_ID": 368,
        "ilce_ADI": null,
        "belde_ID": 0,
        "secim_CEVRESI_ID": 0,
        "yerlesim_YERI_TURU": 0,
        "secilecek_ADAY_SAYISI": 0,
        "il_ID": 47,
        "il_ADI": null,
        "secim_DETAY_ID": 0
    },
    {
        "muhtarlik_ID": 104854,
        "min_SANDIK_NO": "1353",
        "max_SANDIK_NO": "1353",
        "muhtarlik_ADI": "TİMURÇİFTLİĞİ KÖYÜ",
        "cezaevi_ID": 0,
        "id": "368_0_1736",
        "birim_ID": 1736,
        "ilce_ID": 368,
        "ilce_ADI": null,
        "belde_ID": 0,
        "secim_CEVRESI_ID": 0,
        "yerlesim_YERI_TURU": 0,
        "secilecek_ADAY_SAYISI": 0,
        "il_ID": 47,
        "il_ADI": null,
        "secim_DETAY_ID": 0
    },
    {
        "muhtarlik_ID": 104855,
        "min_SANDIK_NO": "1354",
        "max_SANDIK_NO": "1354",
        "muhtarlik_ADI": "TOSUNLU KÖYÜ",
        "cezaevi_ID": 0,
        "id": "368_0_1736",
        "birim_ID": 1736,
        "ilce_ID": 368,
        "ilce_ADI": null,
        "belde_ID": 0,
        "secim_CEVRESI_ID": 0,
        "yerlesim_YERI_TURU": 0,
        "secilecek_ADAY_SAYISI": 0,
        "il_ID": 47,
        "il_ADI": null,
        "secim_DETAY_ID": 0
    },
    {
        "muhtarlik_ID": 104753,
        "min_SANDIK_NO": "1144",
        "max_SANDIK_NO": "1155",
        "muhtarlik_ADI": "TURGUT ÖZAL MAH.",
        "cezaevi_ID": 0,
        "id": "368_0_1736",
        "birim_ID": 1736,
        "ilce_ID": 368,
        "ilce_ADI": null,
        "belde_ID": 0,
        "secim_CEVRESI_ID": 0,
        "yerlesim_YERI_TURU": 0,
        "secilecek_ADAY_SAYISI": 0,
        "il_ID": 47,
        "il_ADI": null,
        "secim_DETAY_ID": 0
    },
    {
        "muhtarlik_ID": 104753,
        "min_SANDIK_NO": "9900",
        "max_SANDIK_NO": "9900",
        "muhtarlik_ADI": "KIZILTEPE K 1 TİPİ KAPALI CEZA İNFAZ KURUMU",
        "cezaevi_ID": 408,
        "id": "368_0_1736",
        "birim_ID": 1736,
        "ilce_ID": 368,
        "ilce_ADI": null,
        "belde_ID": 0,
        "secim_CEVRESI_ID": 0,
        "yerlesim_YERI_TURU": 0,
        "secilecek_ADAY_SAYISI": 0,
        "il_ID": 47,
        "il_ADI": null,
        "secim_DETAY_ID": 0
    },
    {
        "muhtarlik_ID": 104856,
        "min_SANDIK_NO": "1355",
        "max_SANDIK_NO": "1355",
        "muhtarlik_ADI": "TUZLA KÖYÜ",
        "cezaevi_ID": 0,
        "id": "368_0_1736",
        "birim_ID": 1736,
        "ilce_ID": 368,
        "ilce_ADI": null,
        "belde_ID": 0,
        "secim_CEVRESI_ID": 0,
        "yerlesim_YERI_TURU": 0,
        "secilecek_ADAY_SAYISI": 0,
        "il_ID": 47,
        "il_ADI": null,
        "secim_DETAY_ID": 0
    },
    {
        "muhtarlik_ID": 104857,
        "min_SANDIK_NO": "1356",
        "max_SANDIK_NO": "1356",
        "muhtarlik_ADI": "TUZLUCA KÖYÜ",
        "cezaevi_ID": 0,
        "id": "368_0_1736",
        "birim_ID": 1736,
        "ilce_ID": 368,
        "ilce_ADI": null,
        "belde_ID": 0,
        "secim_CEVRESI_ID": 0,
        "yerlesim_YERI_TURU": 0,
        "secilecek_ADAY_SAYISI": 0,
        "il_ID": 47,
        "il_ADI": null,
        "secim_DETAY_ID": 0
    },
    {
        "muhtarlik_ID": 104858,
        "min_SANDIK_NO": "1357",
        "max_SANDIK_NO": "1357",
        "muhtarlik_ADI": "ULAŞLI KÖYÜ",
        "cezaevi_ID": 0,
        "id": "368_0_1736",
        "birim_ID": 1736,
        "ilce_ID": 368,
        "ilce_ADI": null,
        "belde_ID": 0,
        "secim_CEVRESI_ID": 0,
        "yerlesim_YERI_TURU": 0,
        "secilecek_ADAY_SAYISI": 0,
        "il_ID": 47,
        "il_ADI": null,
        "secim_DETAY_ID": 0
    },
    {
        "muhtarlik_ID": 104859,
        "min_SANDIK_NO": "1358",
        "max_SANDIK_NO": "1358",
        "muhtarlik_ADI": "ULUKÖY",
        "cezaevi_ID": 0,
        "id": "368_0_1736",
        "birim_ID": 1736,
        "ilce_ID": 368,
        "ilce_ADI": null,
        "belde_ID": 0,
        "secim_CEVRESI_ID": 0,
        "yerlesim_YERI_TURU": 0,
        "secilecek_ADAY_SAYISI": 0,
        "il_ID": 47,
        "il_ADI": null,
        "secim_DETAY_ID": 0
    },
    {
        "muhtarlik_ID": 104860,
        "min_SANDIK_NO": "1359",
        "max_SANDIK_NO": "1359",
        "muhtarlik_ADI": "UZUNKAYA KÖYÜ",
        "cezaevi_ID": 0,
        "id": "368_0_1736",
        "birim_ID": 1736,
        "ilce_ID": 368,
        "ilce_ADI": null,
        "belde_ID": 0,
        "secim_CEVRESI_ID": 0,
        "yerlesim_YERI_TURU": 0,
        "secilecek_ADAY_SAYISI": 0,
        "il_ID": 47,
        "il_ADI": null,
        "secim_DETAY_ID": 0
    },
    {
        "muhtarlik_ID": 104861,
        "min_SANDIK_NO": "1360",
        "max_SANDIK_NO": "1360",
        "muhtarlik_ADI": "ÜÇEVLER KÖYÜ",
        "cezaevi_ID": 0,
        "id": "368_0_1736",
        "birim_ID": 1736,
        "ilce_ID": 368,
        "ilce_ADI": null,
        "belde_ID": 0,
        "secim_CEVRESI_ID": 0,
        "yerlesim_YERI_TURU": 0,
        "secilecek_ADAY_SAYISI": 0,
        "il_ID": 47,
        "il_ADI": null,
        "secim_DETAY_ID": 0
    },
    {
        "muhtarlik_ID": 104862,
        "min_SANDIK_NO": "1361",
        "max_SANDIK_NO": "1361",
        "muhtarlik_ADI": "ÜLKER KÖYÜ",
        "cezaevi_ID": 0,
        "id": "368_0_1736",
        "birim_ID": 1736,
        "ilce_ID": 368,
        "ilce_ADI": null,
        "belde_ID": 0,
        "secim_CEVRESI_ID": 0,
        "yerlesim_YERI_TURU": 0,
        "secilecek_ADAY_SAYISI": 0,
        "il_ID": 47,
        "il_ADI": null,
        "secim_DETAY_ID": 0
    },
    {
        "muhtarlik_ID": 104863,
        "min_SANDIK_NO": "1362",
        "max_SANDIK_NO": "1362",
        "muhtarlik_ADI": "YALINKILIÇ KÖYÜ",
        "cezaevi_ID": 0,
        "id": "368_0_1736",
        "birim_ID": 1736,
        "ilce_ID": 368,
        "ilce_ADI": null,
        "belde_ID": 0,
        "secim_CEVRESI_ID": 0,
        "yerlesim_YERI_TURU": 0,
        "secilecek_ADAY_SAYISI": 0,
        "il_ID": 47,
        "il_ADI": null,
        "secim_DETAY_ID": 0
    },
    {
        "muhtarlik_ID": 104885,
        "min_SANDIK_NO": "1363",
        "max_SANDIK_NO": "1363",
        "muhtarlik_ADI": "YAMAÇ KÖYÜ",
        "cezaevi_ID": 0,
        "id": "368_0_1736",
        "birim_ID": 1736,
        "ilce_ID": 368,
        "ilce_ADI": null,
        "belde_ID": 0,
        "secim_CEVRESI_ID": 0,
        "yerlesim_YERI_TURU": 0,
        "secilecek_ADAY_SAYISI": 0,
        "il_ID": 47,
        "il_ADI": null,
        "secim_DETAY_ID": 0
    },
    {
        "muhtarlik_ID": 104893,
        "min_SANDIK_NO": "1364",
        "max_SANDIK_NO": "1364",
        "muhtarlik_ADI": "YARIMCA KÖYÜ",
        "cezaevi_ID": 0,
        "id": "368_0_1736",
        "birim_ID": 1736,
        "ilce_ID": 368,
        "ilce_ADI": null,
        "belde_ID": 0,
        "secim_CEVRESI_ID": 0,
        "yerlesim_YERI_TURU": 0,
        "secilecek_ADAY_SAYISI": 0,
        "il_ID": 47,
        "il_ADI": null,
        "secim_DETAY_ID": 0
    },
    {
        "muhtarlik_ID": 124781,
        "min_SANDIK_NO": "1365",
        "max_SANDIK_NO": "1365",
        "muhtarlik_ADI": "YAŞARKÖY",
        "cezaevi_ID": 0,
        "id": "368_0_1736",
        "birim_ID": 1736,
        "ilce_ID": 368,
        "ilce_ADI": null,
        "belde_ID": 0,
        "secim_CEVRESI_ID": 0,
        "yerlesim_YERI_TURU": 0,
        "secilecek_ADAY_SAYISI": 0,
        "il_ID": 47,
        "il_ADI": null,
        "secim_DETAY_ID": 0
    },
    {
        "muhtarlik_ID": 104864,
        "min_SANDIK_NO": "1366",
        "max_SANDIK_NO": "1366",
        "muhtarlik_ADI": "YAYIKLI KÖYÜ",
        "cezaevi_ID": 0,
        "id": "368_0_1736",
        "birim_ID": 1736,
        "ilce_ID": 368,
        "ilce_ADI": null,
        "belde_ID": 0,
        "secim_CEVRESI_ID": 0,
        "yerlesim_YERI_TURU": 0,
        "secilecek_ADAY_SAYISI": 0,
        "il_ID": 47,
        "il_ADI": null,
        "secim_DETAY_ID": 0
    },
    {
        "muhtarlik_ID": 104865,
        "min_SANDIK_NO": "1367",
        "max_SANDIK_NO": "1367",
        "muhtarlik_ADI": "YAYLIM KÖYÜ",
        "cezaevi_ID": 0,
        "id": "368_0_1736",
        "birim_ID": 1736,
        "ilce_ID": 368,
        "ilce_ADI": null,
        "belde_ID": 0,
        "secim_CEVRESI_ID": 0,
        "yerlesim_YERI_TURU": 0,
        "secilecek_ADAY_SAYISI": 0,
        "il_ID": 47,
        "il_ADI": null,
        "secim_DETAY_ID": 0
    },
    {
        "muhtarlik_ID": 104866,
        "min_SANDIK_NO": "1368",
        "max_SANDIK_NO": "1368",
        "muhtarlik_ADI": "YEDİKARDEŞ KÖYÜ",
        "cezaevi_ID": 0,
        "id": "368_0_1736",
        "birim_ID": 1736,
        "ilce_ID": 368,
        "ilce_ADI": null,
        "belde_ID": 0,
        "secim_CEVRESI_ID": 0,
        "yerlesim_YERI_TURU": 0,
        "secilecek_ADAY_SAYISI": 0,
        "il_ID": 47,
        "il_ADI": null,
        "secim_DETAY_ID": 0
    },
    {
        "muhtarlik_ID": 104754,
        "min_SANDIK_NO": "1156",
        "max_SANDIK_NO": "1182",
        "muhtarlik_ADI": "YENİ MAH.",
        "cezaevi_ID": 0,
        "id": "368_0_1736",
        "birim_ID": 1736,
        "ilce_ID": 368,
        "ilce_ADI": null,
        "belde_ID": 0,
        "secim_CEVRESI_ID": 0,
        "yerlesim_YERI_TURU": 0,
        "secilecek_ADAY_SAYISI": 0,
        "il_ID": 47,
        "il_ADI": null,
        "secim_DETAY_ID": 0
    },
    {
        "muhtarlik_ID": 104867,
        "min_SANDIK_NO": "1369",
        "max_SANDIK_NO": "1369",
        "muhtarlik_ADI": "YEŞİLKÖY",
        "cezaevi_ID": 0,
        "id": "368_0_1736",
        "birim_ID": 1736,
        "ilce_ID": 368,
        "ilce_ADI": null,
        "belde_ID": 0,
        "secim_CEVRESI_ID": 0,
        "yerlesim_YERI_TURU": 0,
        "secilecek_ADAY_SAYISI": 0,
        "il_ID": 47,
        "il_ADI": null,
        "secim_DETAY_ID": 0
    },
    {
        "muhtarlik_ID": 104868,
        "min_SANDIK_NO": "1370",
        "max_SANDIK_NO": "1370",
        "muhtarlik_ADI": "YOLALDI KÖYÜ",
        "cezaevi_ID": 0,
        "id": "368_0_1736",
        "birim_ID": 1736,
        "ilce_ID": 368,
        "ilce_ADI": null,
        "belde_ID": 0,
        "secim_CEVRESI_ID": 0,
        "yerlesim_YERI_TURU": 0,
        "secilecek_ADAY_SAYISI": 0,
        "il_ID": 47,
        "il_ADI": null,
        "secim_DETAY_ID": 0
    },
    {
        "muhtarlik_ID": 104869,
        "min_SANDIK_NO": "1371",
        "max_SANDIK_NO": "1371",
        "muhtarlik_ADI": "YOLDERE KÖYÜ",
        "cezaevi_ID": 0,
        "id": "368_0_1736",
        "birim_ID": 1736,
        "ilce_ID": 368,
        "ilce_ADI": null,
        "belde_ID": 0,
        "secim_CEVRESI_ID": 0,
        "yerlesim_YERI_TURU": 0,
        "secilecek_ADAY_SAYISI": 0,
        "il_ID": 47,
        "il_ADI": null,
        "secim_DETAY_ID": 0
    },
    {
        "muhtarlik_ID": 104881,
        "min_SANDIK_NO": "1372",
        "max_SANDIK_NO": "1372",
        "muhtarlik_ADI": "YOLÜSTÜ KÖYÜ",
        "cezaevi_ID": 0,
        "id": "368_0_1736",
        "birim_ID": 1736,
        "ilce_ID": 368,
        "ilce_ADI": null,
        "belde_ID": 0,
        "secim_CEVRESI_ID": 0,
        "yerlesim_YERI_TURU": 0,
        "secilecek_ADAY_SAYISI": 0,
        "il_ID": 47,
        "il_ADI": null,
        "secim_DETAY_ID": 0
    },
    {
        "muhtarlik_ID": 104870,
        "min_SANDIK_NO": "1373",
        "max_SANDIK_NO": "1373",
        "muhtarlik_ADI": "YONCALI KÖYÜ",
        "cezaevi_ID": 0,
        "id": "368_0_1736",
        "birim_ID": 1736,
        "ilce_ID": 368,
        "ilce_ADI": null,
        "belde_ID": 0,
        "secim_CEVRESI_ID": 0,
        "yerlesim_YERI_TURU": 0,
        "secilecek_ADAY_SAYISI": 0,
        "il_ID": 47,
        "il_ADI": null,
        "secim_DETAY_ID": 0
    },
    {
        "muhtarlik_ID": 104871,
        "min_SANDIK_NO": "1374",
        "max_SANDIK_NO": "1374",
        "muhtarlik_ADI": "YUKARIAZIKLI KÖYÜ",
        "cezaevi_ID": 0,
        "id": "368_0_1736",
        "birim_ID": 1736,
        "ilce_ID": 368,
        "ilce_ADI": null,
        "belde_ID": 0,
        "secim_CEVRESI_ID": 0,
        "yerlesim_YERI_TURU": 0,
        "secilecek_ADAY_SAYISI": 0,
        "il_ID": 47,
        "il_ADI": null,
        "secim_DETAY_ID": 0
    },
    {
        "muhtarlik_ID": 104889,
        "min_SANDIK_NO": "1375",
        "max_SANDIK_NO": "1375",
        "muhtarlik_ADI": "YUMRUTAŞ KÖYÜ",
        "cezaevi_ID": 0,
        "id": "368_0_1736",
        "birim_ID": 1736,
        "ilce_ID": 368,
        "ilce_ADI": null,
        "belde_ID": 0,
        "secim_CEVRESI_ID": 0,
        "yerlesim_YERI_TURU": 0,
        "secilecek_ADAY_SAYISI": 0,
        "il_ID": 47,
        "il_ADI": null,
        "secim_DETAY_ID": 0
    },
    {
        "muhtarlik_ID": 104872,
        "min_SANDIK_NO": "1376",
        "max_SANDIK_NO": "1377",
        "muhtarlik_ADI": "YUMURCAK KÖYÜ",
        "cezaevi_ID": 0,
        "id": "368_0_1736",
        "birim_ID": 1736,
        "ilce_ID": 368,
        "ilce_ADI": null,
        "belde_ID": 0,
        "secim_CEVRESI_ID": 0,
        "yerlesim_YERI_TURU": 0,
        "secilecek_ADAY_SAYISI": 0,
        "il_ID": 47,
        "il_ADI": null,
        "secim_DETAY_ID": 0
    },
    {
        "muhtarlik_ID": 104873,
        "min_SANDIK_NO": "1378",
        "max_SANDIK_NO": "1378",
        "muhtarlik_ADI": "YURTDERİ KÖYÜ",
        "cezaevi_ID": 0,
        "id": "368_0_1736",
        "birim_ID": 1736,
        "ilce_ID": 368,
        "ilce_ADI": null,
        "belde_ID": 0,
        "secim_CEVRESI_ID": 0,
        "yerlesim_YERI_TURU": 0,
        "secilecek_ADAY_SAYISI": 0,
        "il_ID": 47,
        "il_ADI": null,
        "secim_DETAY_ID": 0
    },
    {
        "muhtarlik_ID": 104874,
        "min_SANDIK_NO": "1379",
        "max_SANDIK_NO": "1379",
        "muhtarlik_ADI": "YURTÖZÜ KÖYÜ",
        "cezaevi_ID": 0,
        "id": "368_0_1736",
        "birim_ID": 1736,
        "ilce_ID": 368,
        "ilce_ADI": null,
        "belde_ID": 0,
        "secim_CEVRESI_ID": 0,
        "yerlesim_YERI_TURU": 0,
        "secilecek_ADAY_SAYISI": 0,
        "il_ID": 47,
        "il_ADI": null,
        "secim_DETAY_ID": 0
    },
    {
        "muhtarlik_ID": 104875,
        "min_SANDIK_NO": "1202",
        "max_SANDIK_NO": "1204",
        "muhtarlik_ADI": "YÜCELİ-CUMHURİYET MAH.",
        "cezaevi_ID": 0,
        "id": "368_0_1736",
        "birim_ID": 1736,
        "ilce_ID": 368,
        "ilce_ADI": null,
        "belde_ID": 0,
        "secim_CEVRESI_ID": 0,
        "yerlesim_YERI_TURU": 0,
        "secilecek_ADAY_SAYISI": 0,
        "il_ID": 47,
        "il_ADI": null,
        "secim_DETAY_ID": 0
    },
    {
        "muhtarlik_ID": 104876,
        "min_SANDIK_NO": "1380",
        "max_SANDIK_NO": "1380",
        "muhtarlik_ADI": "YÜKSEKTEPE KÖYÜ",
        "cezaevi_ID": 0,
        "id": "368_0_1736",
        "birim_ID": 1736,
        "ilce_ID": 368,
        "ilce_ADI": null,
        "belde_ID": 0,
        "secim_CEVRESI_ID": 0,
        "yerlesim_YERI_TURU": 0,
        "secilecek_ADAY_SAYISI": 0,
        "il_ID": 47,
        "il_ADI": null,
        "secim_DETAY_ID": 0
    },
    {
        "muhtarlik_ID": 104877,
        "min_SANDIK_NO": "1381",
        "max_SANDIK_NO": "1381",
        "muhtarlik_ADI": "ZİYARET KÖYÜ",
        "cezaevi_ID": 0,
        "id": "368_0_1736",
        "birim_ID": 1736,
        "ilce_ID": 368,
        "ilce_ADI": null,
        "belde_ID": 0,
        "secim_CEVRESI_ID": 0,
        "yerlesim_YERI_TURU": 0,
        "secilecek_ADAY_SAYISI": 0,
        "il_ID": 47,
        "il_ADI": null,
        "secim_DETAY_ID": 0
    }
]